[
    "{\"directed\": false, \"multigraph\": false, \"graph\": {}, \"nodes\": [{\"has_standard_radio\": false, \"has_cellular_radio\": false, \"has_satellite_link\": false, \"coord\": [1.5, 0.0], \"id\": \"unit_1\"}], \"links\": []}",
    "{\"directed\": false, \"multigraph\": false, \"graph\": {}, \"nodes\": [{\"has_standard_radio\": false, \"has_cellular_radio\": false, \"has_satellite_link\": false, \"coord\": [3.0, 0.0], \"id\": \"unit_1\"}], \"links\": []}",
    "{\"directed\": false, \"multigraph\": false, \"graph\": {}, \"nodes\": [{\"has_standard_radio\": false, \"has_cellular_radio\": false, \"has_satellite_link\": false, \"coord\": [4.5, 0.0], \"id\": \"unit_1\"}], \"links\": []}",
    "{\"directed\": false, \"multigraph\": false, \"graph\": {}, \"nodes\": [{\"has_standard_radio\": false, \"has_cellular_radio\": false, \"has_satellite_link\": false, \"coord\": [6.0, 0.0], \"id\": \"unit_1\"}], \"links\": []}",
    "{\"directed\": false, \"multigraph\": false, \"graph\": {}, \"nodes\": [{\"has_standard_radio\": false, \"has_cellular_radio\": false, \"has_satellite_link\": false, \"coord\": [7.5, 0.0], \"id\": \"unit_1\"}], \"links\": []}",
    "{\"directed\": false, \"multigraph\": false, \"graph\": {}, \"nodes\": [{\"has_standard_radio\": false, \"has_cellular_radio\": false, \"has_satellite_link\": false, \"coord\": [9.0, 0.0], \"id\": \"unit_1\"}], \"links\": []}",
    "{\"directed\": false, \"multigraph\": false, \"graph\": {}, \"nodes\": [{\"has_standard_radio\": false, \"has_cellular_radio\": false, \"has_satellite_link\": false, \"coord\": [10.5, 0.0], \"id\": \"unit_1\"}], \"links\": []}",
    "{\"directed\": false, \"multigraph\": false, \"graph\": {}, \"nodes\": [{\"has_standard_radio\": false, \"has_cellular_radio\": false, \"has_satellite_link\": false, \"coord\": [12.0, 0.0], \"id\": \"unit_1\"}], \"links\": []}",
    "{\"directed\": false, \"multigraph\": false, \"graph\": {}, \"nodes\": [{\"has_standard_radio\": false, \"has_cellular_radio\": false, \"has_satellite_link\": false, \"coord\": [13.5, 0.0], \"id\": \"unit_1\"}], \"links\": []}",
    "{\"directed\": false, \"multigraph\": false, \"graph\": {}, \"nodes\": [{\"has_standard_radio\": false, \"has_cellular_radio\": false, \"has_satellite_link\": false, \"coord\": [15.0, 0.0], \"id\": \"unit_1\"}], \"links\": []}",
    "{\"directed\": false, \"multigraph\": false, \"graph\": {}, \"nodes\": [{\"has_standard_radio\": false, \"has_cellular_radio\": false, \"has_satellite_link\": false, \"coord\": [16.5, 0.0], \"id\": \"unit_1\"}], \"links\": []}",
    "{\"directed\": false, \"multigraph\": false, \"graph\": {}, \"nodes\": [{\"has_standard_radio\": false, \"has_cellular_radio\": false, \"has_satellite_link\": false, \"coord\": [18.0, 0.0], \"id\": \"unit_1\"}], \"links\": []}",
    "{\"directed\": false, \"multigraph\": false, \"graph\": {}, \"nodes\": [{\"has_standard_radio\": false, \"has_cellular_radio\": false, \"has_satellite_link\": false, \"coord\": [19.5, 0.0], \"id\": \"unit_1\"}], \"links\": []}",
    "{\"directed\": false, \"multigraph\": false, \"graph\": {}, \"nodes\": [{\"has_standard_radio\": false, \"has_cellular_radio\": false, \"has_satellite_link\": false, \"coord\": [21.0, 0.0], \"id\": \"unit_1\"}], \"links\": []}",
    "{\"directed\": false, \"multigraph\": false, \"graph\": {}, \"nodes\": [{\"has_standard_radio\": false, \"has_cellular_radio\": false, \"has_satellite_link\": false, \"coord\": [22.5, 0.0], \"id\": \"unit_1\"}], \"links\": []}",
    "{\"directed\": false, \"multigraph\": false, \"graph\": {}, \"nodes\": [{\"has_standard_radio\": false, \"has_cellular_radio\": false, \"has_satellite_link\": false, \"coord\": [24.0, 0.0], \"id\": \"unit_1\"}], \"links\": []}",
    "{\"directed\": false, \"multigraph\": false, \"graph\": {}, \"nodes\": [{\"has_standard_radio\": false, \"has_cellular_radio\": false, \"has_satellite_link\": false, \"coord\": [25.5, 0.0], \"id\": \"unit_1\"}], \"links\": []}",
    "{\"directed\": false, \"multigraph\": false, \"graph\": {}, \"nodes\": [{\"has_standard_radio\": false, \"has_cellular_radio\": false, \"has_satellite_link\": false, \"coord\": [27.0, 0.0], \"id\": \"unit_1\"}], \"links\": []}",
    "{\"directed\": false, \"multigraph\": false, \"graph\": {}, \"nodes\": [{\"has_standard_radio\": false, \"has_cellular_radio\": false, \"has_satellite_link\": false, \"coord\": [28.5, 0.0], \"id\": \"unit_1\"}], \"links\": []}",
    "{\"directed\": false, \"multigraph\": false, \"graph\": {}, \"nodes\": [{\"has_standard_radio\": false, \"has_cellular_radio\": false, \"has_satellite_link\": false, \"coord\": [30.0, 0.0], \"id\": \"unit_1\"}], \"links\": []}",
    "{\"directed\": false, \"multigraph\": false, \"graph\": {}, \"nodes\": [{\"has_standard_radio\": false, \"has_cellular_radio\": false, \"has_satellite_link\": false, \"coord\": [31.5, 0.0], \"id\": \"unit_1\"}], \"links\": []}",
    "{\"directed\": false, \"multigraph\": false, \"graph\": {}, \"nodes\": [{\"has_standard_radio\": false, \"has_cellular_radio\": false, \"has_satellite_link\": false, \"coord\": [33.0, 0.0], \"id\": \"unit_1\"}], \"links\": []}",
    "{\"directed\": false, \"multigraph\": false, \"graph\": {}, \"nodes\": [{\"has_standard_radio\": false, \"has_cellular_radio\": false, \"has_satellite_link\": false, \"coord\": [34.5, 0.0], \"id\": \"unit_1\"}], \"links\": []}",
    "{\"directed\": false, \"multigraph\": false, \"graph\": {}, \"nodes\": [{\"has_standard_radio\": false, \"has_cellular_radio\": false, \"has_satellite_link\": false, \"coord\": [36.0, 0.0], \"id\": \"unit_1\"}], \"links\": []}",
    "{\"directed\": false, \"multigraph\": false, \"graph\": {}, \"nodes\": [{\"has_standard_radio\": false, \"has_cellular_radio\": false, \"has_satellite_link\": false, \"coord\": [37.5, 0.0], \"id\": \"unit_1\"}], \"links\": []}",
    "{\"directed\": false, \"multigraph\": false, \"graph\": {}, \"nodes\": [{\"has_standard_radio\": false, \"has_cellular_radio\": false, \"has_satellite_link\": false, \"coord\": [39.0, 0.0], \"id\": \"unit_1\"}], \"links\": []}",
    "{\"directed\": false, \"multigraph\": false, \"graph\": {}, \"nodes\": [{\"has_standard_radio\": false, \"has_cellular_radio\": false, \"has_satellite_link\": false, \"coord\": [40.5, 0.0], \"id\": \"unit_1\"}], \"links\": []}",
    "{\"directed\": false, \"multigraph\": false, \"graph\": {}, \"nodes\": [{\"has_standard_radio\": false, \"has_cellular_radio\": false, \"has_satellite_link\": false, \"coord\": [42.0, 0.0], \"id\": \"unit_1\"}], \"links\": []}",
    "{\"directed\": false, \"multigraph\": false, \"graph\": {}, \"nodes\": [{\"has_standard_radio\": false, \"has_cellular_radio\": false, \"has_satellite_link\": false, \"coord\": [43.5, 0.0], \"id\": \"unit_1\"}], \"links\": []}",
    "{\"directed\": false, \"multigraph\": false, \"graph\": {}, \"nodes\": [{\"has_standard_radio\": false, \"has_cellular_radio\": false, \"has_satellite_link\": false, \"coord\": [45.0, 0.0], \"id\": \"unit_1\"}], \"links\": []}",
    "{\"directed\": false, \"multigraph\": false, \"graph\": {}, \"nodes\": [{\"has_standard_radio\": false, \"has_cellular_radio\": false, \"has_satellite_link\": false, \"coord\": [46.5, 0.0], \"id\": \"unit_1\"}], \"links\": []}",
    "{\"directed\": false, \"multigraph\": false, \"graph\": {}, \"nodes\": [{\"has_standard_radio\": false, \"has_cellular_radio\": false, \"has_satellite_link\": false, \"coord\": [48.0, 0.0], \"id\": \"unit_1\"}], \"links\": []}",
    "{\"directed\": false, \"multigraph\": false, \"graph\": {}, \"nodes\": [{\"has_standard_radio\": false, \"has_cellular_radio\": false, \"has_satellite_link\": false, \"coord\": [49.5, 0.0], \"id\": \"unit_1\"}], \"links\": []}",
    "{\"directed\": false, \"multigraph\": false, \"graph\": {}, \"nodes\": [{\"has_standard_radio\": false, \"has_cellular_radio\": false, \"has_satellite_link\": false, \"coord\": [50.0, 1.0000000000000002], \"id\": \"unit_1\"}], \"links\": []}",
    "{\"directed\": false, \"multigraph\": false, \"graph\": {}, \"nodes\": [{\"has_standard_radio\": false, \"has_cellular_radio\": false, \"has_satellite_link\": false, \"coord\": [50.0, 2.5], \"id\": \"unit_1\"}], \"links\": []}",
    "{\"directed\": false, \"multigraph\": false, \"graph\": {}, \"nodes\": [{\"has_standard_radio\": false, \"has_cellular_radio\": false, \"has_satellite_link\": false, \"coord\": [50.0, 4.0], \"id\": \"unit_1\"}], \"links\": []}",
    "{\"directed\": false, \"multigraph\": false, \"graph\": {}, \"nodes\": [{\"has_standard_radio\": false, \"has_cellular_radio\": false, \"has_satellite_link\": false, \"coord\": [50.0, 5.5], \"id\": \"unit_1\"}], \"links\": []}",
    "{\"directed\": false, \"multigraph\": false, \"graph\": {}, \"nodes\": [{\"has_standard_radio\": false, \"has_cellular_radio\": false, \"has_satellite_link\": false, \"coord\": [50.0, 7.0], \"id\": \"unit_1\"}], \"links\": []}",
    "{\"directed\": false, \"multigraph\": false, \"graph\": {}, \"nodes\": [{\"has_standard_radio\": false, \"has_cellular_radio\": false, \"has_satellite_link\": false, \"coord\": [50.0, 8.5], \"id\": \"unit_1\"}], \"links\": []}",
    "{\"directed\": false, \"multigraph\": false, \"graph\": {}, \"nodes\": [{\"has_standard_radio\": false, \"has_cellular_radio\": false, \"has_satellite_link\": false, \"coord\": [50.0, 10.0], \"id\": \"unit_1\"}], \"links\": []}",
    "{\"directed\": false, \"multigraph\": false, \"graph\": {}, \"nodes\": [{\"has_standard_radio\": false, \"has_cellular_radio\": false, \"has_satellite_link\": false, \"coord\": [48.93933982822018, 11.060660171779821], \"id\": \"unit_1\"}], \"links\": []}",
    "{\"directed\": false, \"multigraph\": false, \"graph\": {}, \"nodes\": [{\"has_standard_radio\": false, \"has_cellular_radio\": false, \"has_satellite_link\": false, \"coord\": [47.878679656440355, 12.121320343559642], \"id\": \"unit_1\"}], \"links\": []}",
    "{\"directed\": false, \"multigraph\": false, \"graph\": {}, \"nodes\": [{\"has_standard_radio\": false, \"has_cellular_radio\": false, \"has_satellite_link\": false, \"coord\": [46.81801948466053, 13.181980515339463], \"id\": \"unit_1\"}], \"links\": []}",
    "{\"directed\": false, \"multigraph\": false, \"graph\": {}, \"nodes\": [{\"has_standard_radio\": false, \"has_cellular_radio\": false, \"has_satellite_link\": false, \"coord\": [45.75735931288071, 14.242640687119284], \"id\": \"unit_1\"}], \"links\": []}",
    "{\"directed\": false, \"multigraph\": false, \"graph\": {}, \"nodes\": [{\"has_standard_radio\": false, \"has_cellular_radio\": false, \"has_satellite_link\": false, \"coord\": [44.696699141100886, 15.303300858899107], \"id\": \"unit_1\"}], \"links\": []}",
    "{\"directed\": false, \"multigraph\": false, \"graph\": {}, \"nodes\": [{\"has_standard_radio\": false, \"has_cellular_radio\": false, \"has_satellite_link\": false, \"coord\": [43.63603896932106, 16.36396103067893], \"id\": \"unit_1\"}], \"links\": []}",
    "{\"directed\": false, \"multigraph\": false, \"graph\": {}, \"nodes\": [{\"has_standard_radio\": false, \"has_cellular_radio\": false, \"has_satellite_link\": false, \"coord\": [42.57537879754124, 17.424621202458752], \"id\": \"unit_1\"}], \"links\": []}",
    "{\"directed\": false, \"multigraph\": false, \"graph\": {}, \"nodes\": [{\"has_standard_radio\": false, \"has_cellular_radio\": false, \"has_satellite_link\": false, \"coord\": [41.51471862576142, 18.485281374238575], \"id\": \"unit_1\"}], \"links\": []}",
    "{\"directed\": false, \"multigraph\": false, \"graph\": {}, \"nodes\": [{\"has_standard_radio\": false, \"has_cellular_radio\": false, \"has_satellite_link\": false, \"coord\": [40.4540584539816, 19.545941546018398], \"id\": \"unit_1\"}], \"links\": []}",
    "{\"directed\": false, \"multigraph\": false, \"graph\": {}, \"nodes\": [{\"has_standard_radio\": false, \"has_cellular_radio\": false, \"has_satellite_link\": false, \"coord\": [39.39339828220178, 20.60660171779822], \"id\": \"unit_1\"}], \"links\": []}",
    "{\"directed\": false, \"multigraph\": false, \"graph\": {}, \"nodes\": [{\"has_standard_radio\": false, \"has_cellular_radio\": false, \"has_satellite_link\": false, \"coord\": [38.33273811042196, 21.667261889578043], \"id\": \"unit_1\"}], \"links\": []}",
    "{\"directed\": false, \"multigraph\": false, \"graph\": {}, \"nodes\": [{\"has_standard_radio\": false, \"has_cellular_radio\": false, \"has_satellite_link\": false, \"coord\": [37.272077938642134, 22.727922061357866], \"id\": \"unit_1\"}], \"links\": []}",
    "{\"directed\": false, \"multigraph\": false, \"graph\": {}, \"nodes\": [{\"has_standard_radio\": false, \"has_cellular_radio\": false, \"has_satellite_link\": false, \"coord\": [36.21141776686231, 23.78858223313769], \"id\": \"unit_1\"}], \"links\": []}",
    "{\"directed\": false, \"multigraph\": false, \"graph\": {}, \"nodes\": [{\"has_standard_radio\": false, \"has_cellular_radio\": false, \"has_satellite_link\": false, \"coord\": [35.15075759508249, 24.84924240491751], \"id\": \"unit_1\"}], \"links\": []}",
    "{\"directed\": false, \"multigraph\": false, \"graph\": {}, \"nodes\": [{\"has_standard_radio\": false, \"has_cellular_radio\": false, \"has_satellite_link\": false, \"coord\": [34.090097423302666, 25.909902576697334], \"id\": \"unit_1\"}], \"links\": []}",
    "{\"directed\": false, \"multigraph\": false, \"graph\": {}, \"nodes\": [{\"has_standard_radio\": false, \"has_cellular_radio\": false, \"has_satellite_link\": false, \"coord\": [33.02943725152284, 26.970562748477157], \"id\": \"unit_1\"}], \"links\": []}",
    "{\"directed\": false, \"multigraph\": false, \"graph\": {}, \"nodes\": [{\"has_standard_radio\": false, \"has_cellular_radio\": false, \"has_satellite_link\": false, \"coord\": [31.96877707974302, 28.03122292025698], \"id\": \"unit_1\"}], \"links\": []}",
    "{\"directed\": false, \"multigraph\": false, \"graph\": {}, \"nodes\": [{\"has_standard_radio\": false, \"has_cellular_radio\": false, \"has_satellite_link\": false, \"coord\": [30.908116907963198, 29.091883092036802], \"id\": \"unit_1\"}], \"links\": []}",
    "{\"directed\": false, \"multigraph\": false, \"graph\": {}, \"nodes\": [{\"has_standard_radio\": false, \"has_cellular_radio\": false, \"has_satellite_link\": false, \"coord\": [29.847456736183375, 30.152543263816625], \"id\": \"unit_1\"}], \"links\": []}",
    "{\"directed\": false, \"multigraph\": false, \"graph\": {}, \"nodes\": [{\"has_standard_radio\": false, \"has_cellular_radio\": false, \"has_satellite_link\": false, \"coord\": [28.786796564403552, 31.213203435596448], \"id\": \"unit_1\"}], \"links\": []}",
    "{\"directed\": false, \"multigraph\": false, \"graph\": {}, \"nodes\": [{\"has_standard_radio\": false, \"has_cellular_radio\": false, \"has_satellite_link\": false, \"coord\": [27.72613639262373, 32.27386360737627], \"id\": \"unit_1\"}], \"links\": []}",
    "{\"directed\": false, \"multigraph\": false, \"graph\": {}, \"nodes\": [{\"has_standard_radio\": false, \"has_cellular_radio\": false, \"has_satellite_link\": false, \"coord\": [26.665476220843907, 33.33452377915609], \"id\": \"unit_1\"}], \"links\": []}",
    "{\"directed\": false, \"multigraph\": false, \"graph\": {}, \"nodes\": [{\"has_standard_radio\": false, \"has_cellular_radio\": false, \"has_satellite_link\": false, \"coord\": [25.604816049064084, 34.395183950935916], \"id\": \"unit_1\"}], \"links\": []}",
    "{\"directed\": false, \"multigraph\": false, \"graph\": {}, \"nodes\": [{\"has_standard_radio\": false, \"has_cellular_radio\": false, \"has_satellite_link\": false, \"coord\": [24.54415587728426, 35.45584412271574], \"id\": \"unit_1\"}], \"links\": []}",
    "{\"directed\": false, \"multigraph\": false, \"graph\": {}, \"nodes\": [{\"has_standard_radio\": false, \"has_cellular_radio\": false, \"has_satellite_link\": false, \"coord\": [23.48349570550444, 36.51650429449556], \"id\": \"unit_1\"}], \"links\": []}",
    "{\"directed\": false, \"multigraph\": false, \"graph\": {}, \"nodes\": [{\"has_standard_radio\": false, \"has_cellular_radio\": false, \"has_satellite_link\": false, \"coord\": [22.422835533724616, 37.577164466275384], \"id\": \"unit_1\"}], \"links\": []}",
    "{\"directed\": false, \"multigraph\": false, \"graph\": {}, \"nodes\": [{\"has_standard_radio\": false, \"has_cellular_radio\": false, \"has_satellite_link\": false, \"coord\": [21.362175361944793, 38.63782463805521], \"id\": \"unit_1\"}], \"links\": []}",
    "{\"directed\": false, \"multigraph\": false, \"graph\": {}, \"nodes\": [{\"has_standard_radio\": false, \"has_cellular_radio\": false, \"has_satellite_link\": false, \"coord\": [20.30151519016497, 39.69848480983503], \"id\": \"unit_1\"}], \"links\": []}",
    "{\"directed\": false, \"multigraph\": false, \"graph\": {}, \"nodes\": [{\"has_standard_radio\": false, \"has_cellular_radio\": false, \"has_satellite_link\": false, \"coord\": [19.240855018385147, 40.75914498161485], \"id\": \"unit_1\"}], \"links\": []}",
    "{\"directed\": false, \"multigraph\": false, \"graph\": {}, \"nodes\": [{\"has_standard_radio\": false, \"has_cellular_radio\": false, \"has_satellite_link\": false, \"coord\": [18.180194846605325, 41.819805153394675], \"id\": \"unit_1\"}], \"links\": []}",
    "{\"directed\": false, \"multigraph\": false, \"graph\": {}, \"nodes\": [{\"has_standard_radio\": false, \"has_cellular_radio\": false, \"has_satellite_link\": false, \"coord\": [17.119534674825502, 42.8804653251745], \"id\": \"unit_1\"}], \"links\": []}",
    "{\"directed\": false, \"multigraph\": false, \"graph\": {}, \"nodes\": [{\"has_standard_radio\": false, \"has_cellular_radio\": false, \"has_satellite_link\": false, \"coord\": [16.05887450304568, 43.94112549695432], \"id\": \"unit_1\"}], \"links\": []}",
    "{\"directed\": false, \"multigraph\": false, \"graph\": {}, \"nodes\": [{\"has_standard_radio\": false, \"has_cellular_radio\": false, \"has_satellite_link\": false, \"coord\": [14.998214331265858, 45.00178566873414], \"id\": \"unit_1\"}], \"links\": []}",
    "{\"directed\": false, \"multigraph\": false, \"graph\": {}, \"nodes\": [{\"has_standard_radio\": false, \"has_cellular_radio\": false, \"has_satellite_link\": false, \"coord\": [13.937554159486037, 46.062445840513966], \"id\": \"unit_1\"}], \"links\": []}",
    "{\"directed\": false, \"multigraph\": false, \"graph\": {}, \"nodes\": [{\"has_standard_radio\": false, \"has_cellular_radio\": false, \"has_satellite_link\": false, \"coord\": [12.876893987706216, 47.12310601229379], \"id\": \"unit_1\"}], \"links\": []}",
    "{\"directed\": false, \"multigraph\": false, \"graph\": {}, \"nodes\": [{\"has_standard_radio\": false, \"has_cellular_radio\": false, \"has_satellite_link\": false, \"coord\": [11.816233815926394, 48.18376618407361], \"id\": \"unit_1\"}], \"links\": []}",
    "{\"directed\": false, \"multigraph\": false, \"graph\": {}, \"nodes\": [{\"has_standard_radio\": false, \"has_cellular_radio\": false, \"has_satellite_link\": false, \"coord\": [10.75557364414657, 49.244426355853435], \"id\": \"unit_1\"}], \"links\": []}",
    "{\"directed\": false, \"multigraph\": false, \"graph\": {}, \"nodes\": [{\"has_standard_radio\": false, \"has_cellular_radio\": false, \"has_satellite_link\": false, \"coord\": [10.305086527633252, 50.30508652763325], \"id\": \"unit_1\"}], \"links\": []}",
    "{\"directed\": false, \"multigraph\": false, \"graph\": {}, \"nodes\": [{\"has_standard_radio\": false, \"has_cellular_radio\": false, \"has_satellite_link\": false, \"coord\": [11.365746699413073, 51.36574669941307], \"id\": \"unit_1\"}], \"links\": []}",
    "{\"directed\": false, \"multigraph\": false, \"graph\": {}, \"nodes\": [{\"has_standard_radio\": false, \"has_cellular_radio\": false, \"has_satellite_link\": false, \"coord\": [12.426406871192894, 52.426406871192896], \"id\": \"unit_1\"}], \"links\": []}",
    "{\"directed\": false, \"multigraph\": false, \"graph\": {}, \"nodes\": [{\"has_standard_radio\": false, \"has_cellular_radio\": false, \"has_satellite_link\": false, \"coord\": [13.487067042972715, 53.48706704297272], \"id\": \"unit_1\"}], \"links\": []}",
    "{\"directed\": false, \"multigraph\": false, \"graph\": {}, \"nodes\": [{\"has_standard_radio\": false, \"has_cellular_radio\": false, \"has_satellite_link\": false, \"coord\": [14.547727214752536, 54.54772721475254], \"id\": \"unit_1\"}], \"links\": []}",
    "{\"directed\": false, \"multigraph\": false, \"graph\": {}, \"nodes\": [{\"has_standard_radio\": false, \"has_cellular_radio\": false, \"has_satellite_link\": false, \"coord\": [15.608387386532357, 55.608387386532364], \"id\": \"unit_1\"}], \"links\": []}",
    "{\"directed\": false, \"multigraph\": false, \"graph\": {}, \"nodes\": [{\"has_standard_radio\": false, \"has_cellular_radio\": false, \"has_satellite_link\": false, \"coord\": [16.66904755831218, 56.66904755831219], \"id\": \"unit_1\"}], \"links\": []}",
    "{\"directed\": false, \"multigraph\": false, \"graph\": {}, \"nodes\": [{\"has_standard_radio\": false, \"has_cellular_radio\": false, \"has_satellite_link\": false, \"coord\": [17.729707730092002, 57.72970773009201], \"id\": \"unit_1\"}], \"links\": []}",
    "{\"directed\": false, \"multigraph\": false, \"graph\": {}, \"nodes\": [{\"has_standard_radio\": false, \"has_cellular_radio\": false, \"has_satellite_link\": false, \"coord\": [18.790367901871825, 58.79036790187183], \"id\": \"unit_1\"}], \"links\": []}",
    "{\"directed\": false, \"multigraph\": false, \"graph\": {}, \"nodes\": [{\"has_standard_radio\": false, \"has_cellular_radio\": false, \"has_satellite_link\": false, \"coord\": [19.851028073651648, 59.85102807365165], \"id\": \"unit_1\"}], \"links\": []}",
    "{\"directed\": false, \"multigraph\": false, \"graph\": {}, \"nodes\": [{\"has_standard_radio\": false, \"has_cellular_radio\": false, \"has_satellite_link\": false, \"coord\": [20.91168824543147, 60.91168824543147], \"id\": \"unit_1\"}], \"links\": []}",
    "{\"directed\": false, \"multigraph\": false, \"graph\": {}, \"nodes\": [{\"has_standard_radio\": false, \"has_cellular_radio\": false, \"has_satellite_link\": false, \"coord\": [21.972348417211293, 61.97234841721129], \"id\": \"unit_1\"}], \"links\": []}",
    "{\"directed\": false, \"multigraph\": false, \"graph\": {}, \"nodes\": [{\"has_standard_radio\": false, \"has_cellular_radio\": false, \"has_satellite_link\": false, \"coord\": [23.033008588991116, 63.033008588991116], \"id\": \"unit_1\"}], \"links\": []}",
    "{\"directed\": false, \"multigraph\": false, \"graph\": {}, \"nodes\": [{\"has_standard_radio\": false, \"has_cellular_radio\": false, \"has_satellite_link\": false, \"coord\": [24.09366876077094, 64.09366876077094], \"id\": \"unit_1\"}], \"links\": []}",
    "{\"directed\": false, \"multigraph\": false, \"graph\": {}, \"nodes\": [{\"has_standard_radio\": false, \"has_cellular_radio\": false, \"has_satellite_link\": false, \"coord\": [25.15432893255076, 65.15432893255075], \"id\": \"unit_1\"}], \"links\": []}",
    "{\"directed\": false, \"multigraph\": false, \"graph\": {}, \"nodes\": [{\"has_standard_radio\": false, \"has_cellular_radio\": false, \"has_satellite_link\": false, \"coord\": [26.21498910433058, 66.21498910433057], \"id\": \"unit_1\"}], \"links\": []}",
    "{\"directed\": false, \"multigraph\": false, \"graph\": {}, \"nodes\": [{\"has_standard_radio\": false, \"has_cellular_radio\": false, \"has_satellite_link\": false, \"coord\": [27.2756492761104, 67.27564927611039], \"id\": \"unit_1\"}], \"links\": []}",
    "{\"directed\": false, \"multigraph\": false, \"graph\": {}, \"nodes\": [{\"has_standard_radio\": false, \"has_cellular_radio\": false, \"has_satellite_link\": false, \"coord\": [28.33630944789022, 68.33630944789022], \"id\": \"unit_1\"}], \"links\": []}",
    "{\"directed\": false, \"multigraph\": false, \"graph\": {}, \"nodes\": [{\"has_standard_radio\": false, \"has_cellular_radio\": false, \"has_satellite_link\": false, \"coord\": [29.39696961967004, 69.39696961967003], \"id\": \"unit_1\"}], \"links\": []}",
    "{\"directed\": false, \"multigraph\": false, \"graph\": {}, \"nodes\": [{\"has_standard_radio\": false, \"has_cellular_radio\": false, \"has_satellite_link\": false, \"coord\": [30.457629791449857, 70.45762979144986], \"id\": \"unit_1\"}], \"links\": []}",
    "{\"directed\": false, \"multigraph\": false, \"graph\": {}, \"nodes\": [{\"has_standard_radio\": false, \"has_cellular_radio\": false, \"has_satellite_link\": false, \"coord\": [31.51828996322968, 71.51828996322968], \"id\": \"unit_1\"}], \"links\": []}",
    "{\"directed\": false, \"multigraph\": false, \"graph\": {}, \"nodes\": [{\"has_standard_radio\": false, \"has_cellular_radio\": false, \"has_satellite_link\": false, \"coord\": [32.5789501350095, 72.57895013500949], \"id\": \"unit_1\"}], \"links\": []}",
    "{\"directed\": false, \"multigraph\": false, \"graph\": {}, \"nodes\": [{\"has_standard_radio\": false, \"has_cellular_radio\": false, \"has_satellite_link\": false, \"coord\": [33.63961030678932, 73.63961030678931], \"id\": \"unit_1\"}], \"links\": []}",
    "{\"directed\": false, \"multigraph\": false, \"graph\": {}, \"nodes\": [{\"has_standard_radio\": false, \"has_cellular_radio\": false, \"has_satellite_link\": false, \"coord\": [34.700270478569145, 74.70027047856912], \"id\": \"unit_1\"}], \"links\": []}",
    "{\"directed\": false, \"multigraph\": false, \"graph\": {}, \"nodes\": [{\"has_standard_radio\": false, \"has_cellular_radio\": false, \"has_satellite_link\": false, \"coord\": [35.76093065034897, 75.76093065034895], \"id\": \"unit_1\"}], \"links\": []}",
    "{\"directed\": false, \"multigraph\": false, \"graph\": {}, \"nodes\": [{\"has_standard_radio\": false, \"has_cellular_radio\": false, \"has_satellite_link\": false, \"coord\": [36.82159082212879, 76.82159082212878], \"id\": \"unit_1\"}], \"links\": []}",
    "{\"directed\": false, \"multigraph\": false, \"graph\": {}, \"nodes\": [{\"has_standard_radio\": false, \"has_cellular_radio\": false, \"has_satellite_link\": false, \"coord\": [37.88225099390861, 77.8822509939086], \"id\": \"unit_1\"}], \"links\": []}",
    "{\"directed\": false, \"multigraph\": false, \"graph\": {}, \"nodes\": [{\"has_standard_radio\": false, \"has_cellular_radio\": false, \"has_satellite_link\": false, \"coord\": [38.94291116568843, 78.94291116568843], \"id\": \"unit_1\"}], \"links\": []}",
    "{\"directed\": false, \"multigraph\": false, \"graph\": {}, \"nodes\": [{\"has_standard_radio\": false, \"has_cellular_radio\": false, \"has_satellite_link\": false, \"coord\": [40.00357133746825, 80.00357133746824], \"id\": \"unit_1\"}], \"links\": []}",
    "{\"directed\": false, \"multigraph\": false, \"graph\": {}, \"nodes\": [{\"has_standard_radio\": false, \"has_cellular_radio\": false, \"has_satellite_link\": false, \"coord\": [41.064231509248074, 81.06423150924806], \"id\": \"unit_1\"}], \"links\": []}",
    "{\"directed\": false, \"multigraph\": false, \"graph\": {}, \"nodes\": [{\"has_standard_radio\": false, \"has_cellular_radio\": false, \"has_satellite_link\": false, \"coord\": [42.1248916810279, 82.12489168102788], \"id\": \"unit_1\"}], \"links\": []}",
    "{\"directed\": false, \"multigraph\": false, \"graph\": {}, \"nodes\": [{\"has_standard_radio\": false, \"has_cellular_radio\": false, \"has_satellite_link\": false, \"coord\": [43.18555185280772, 83.18555185280769], \"id\": \"unit_1\"}], \"links\": []}",
    "{\"directed\": false, \"multigraph\": false, \"graph\": {}, \"nodes\": [{\"has_standard_radio\": false, \"has_cellular_radio\": false, \"has_satellite_link\": false, \"coord\": [44.246212024587535, 84.24621202458752], \"id\": \"unit_1\"}], \"links\": []}",
    "{\"directed\": false, \"multigraph\": false, \"graph\": {}, \"nodes\": [{\"has_standard_radio\": false, \"has_cellular_radio\": false, \"has_satellite_link\": false, \"coord\": [45.30687219636736, 85.30687219636735], \"id\": \"unit_1\"}], \"links\": []}",
    "{\"directed\": false, \"multigraph\": false, \"graph\": {}, \"nodes\": [{\"has_standard_radio\": false, \"has_cellular_radio\": false, \"has_satellite_link\": false, \"coord\": [46.36753236814718, 86.36753236814717], \"id\": \"unit_1\"}], \"links\": []}",
    "{\"directed\": false, \"multigraph\": false, \"graph\": {}, \"nodes\": [{\"has_standard_radio\": false, \"has_cellular_radio\": false, \"has_satellite_link\": false, \"coord\": [47.428192539927, 87.428192539927], \"id\": \"unit_1\"}], \"links\": []}",
    "{\"directed\": false, \"multigraph\": false, \"graph\": {}, \"nodes\": [{\"has_standard_radio\": false, \"has_cellular_radio\": false, \"has_satellite_link\": false, \"coord\": [48.48885271170682, 88.48885271170681], \"id\": \"unit_1\"}], \"links\": []}",
    "{\"directed\": false, \"multigraph\": false, \"graph\": {}, \"nodes\": [{\"has_standard_radio\": false, \"has_cellular_radio\": false, \"has_satellite_link\": false, \"coord\": [49.549512883486635, 89.54951288348664], \"id\": \"unit_1\"}], \"links\": []}",
    "{\"directed\": false, \"multigraph\": false, \"graph\": {}, \"nodes\": [{\"has_standard_radio\": false, \"has_cellular_radio\": false, \"has_satellite_link\": false, \"coord\": [50.0, 90.86291501015246], \"id\": \"unit_1\"}], \"links\": []}",
    "{\"directed\": false, \"multigraph\": false, \"graph\": {}, \"nodes\": [{\"has_standard_radio\": false, \"has_cellular_radio\": false, \"has_satellite_link\": false, \"coord\": [50.0, 92.36291501015246], \"id\": \"unit_1\"}], \"links\": []}",
    "{\"directed\": false, \"multigraph\": false, \"graph\": {}, \"nodes\": [{\"has_standard_radio\": false, \"has_cellular_radio\": false, \"has_satellite_link\": false, \"coord\": [50.0, 93.86291501015246], \"id\": \"unit_1\"}], \"links\": []}",
    "{\"directed\": false, \"multigraph\": false, \"graph\": {}, \"nodes\": [{\"has_standard_radio\": false, \"has_cellular_radio\": false, \"has_satellite_link\": false, \"coord\": [50.0, 95.0], \"id\": \"unit_1\"}], \"links\": []}",
    "{\"directed\": false, \"multigraph\": false, \"graph\": {}, \"nodes\": [{\"has_standard_radio\": false, \"has_cellular_radio\": false, \"has_satellite_link\": false, \"coord\": [50.0, 95.0], \"id\": \"unit_1\"}], \"links\": []}",
    "{\"directed\": false, \"multigraph\": false, \"graph\": {}, \"nodes\": [{\"has_standard_radio\": false, \"has_cellular_radio\": false, \"has_satellite_link\": false, \"coord\": [50.0, 95.0], \"id\": \"unit_1\"}], \"links\": []}",
    "{\"directed\": false, \"multigraph\": false, \"graph\": {}, \"nodes\": [{\"has_standard_radio\": false, \"has_cellular_radio\": false, \"has_satellite_link\": false, \"coord\": [50.0, 95.0], \"id\": \"unit_1\"}], \"links\": []}",
    "{\"directed\": false, \"multigraph\": false, \"graph\": {}, \"nodes\": [{\"has_standard_radio\": false, \"has_cellular_radio\": false, \"has_satellite_link\": false, \"coord\": [50.0, 95.0], \"id\": \"unit_1\"}], \"links\": []}",
    "{\"directed\": false, \"multigraph\": false, \"graph\": {}, \"nodes\": [{\"has_standard_radio\": false, \"has_cellular_radio\": false, \"has_satellite_link\": false, \"coord\": [50.0, 95.0], \"id\": \"unit_1\"}], \"links\": []}",
    "{\"directed\": false, \"multigraph\": false, \"graph\": {}, \"nodes\": [{\"has_standard_radio\": false, \"has_cellular_radio\": false, \"has_satellite_link\": false, \"coord\": [50.0, 95.0], \"id\": \"unit_1\"}], \"links\": []}",
    "{\"directed\": false, \"multigraph\": false, \"graph\": {}, \"nodes\": [{\"has_standard_radio\": false, \"has_cellular_radio\": false, \"has_satellite_link\": false, \"coord\": [50.0, 95.0], \"id\": \"unit_1\"}], \"links\": []}",
    "{\"directed\": false, \"multigraph\": false, \"graph\": {}, \"nodes\": [{\"has_standard_radio\": false, \"has_cellular_radio\": false, \"has_satellite_link\": false, \"coord\": [50.0, 95.0], \"id\": \"unit_1\"}], \"links\": []}",
    "{\"directed\": false, \"multigraph\": false, \"graph\": {}, \"nodes\": [{\"has_standard_radio\": false, \"has_cellular_radio\": false, \"has_satellite_link\": false, \"coord\": [50.0, 95.0], \"id\": \"unit_1\"}], \"links\": []}",
    "{\"directed\": false, \"multigraph\": false, \"graph\": {}, \"nodes\": [{\"has_standard_radio\": false, \"has_cellular_radio\": false, \"has_satellite_link\": false, \"coord\": [50.0, 95.0], \"id\": \"unit_1\"}], \"links\": []}",
    "{\"directed\": false, \"multigraph\": false, \"graph\": {}, \"nodes\": [{\"has_standard_radio\": false, \"has_cellular_radio\": false, \"has_satellite_link\": false, \"coord\": [50.0, 95.0], \"id\": \"unit_1\"}], \"links\": []}",
    "{\"directed\": false, \"multigraph\": false, \"graph\": {}, \"nodes\": [{\"has_standard_radio\": false, \"has_cellular_radio\": false, \"has_satellite_link\": false, \"coord\": [50.0, 95.0], \"id\": \"unit_1\"}], \"links\": []}",
    "{\"directed\": false, \"multigraph\": false, \"graph\": {}, \"nodes\": [{\"has_standard_radio\": false, \"has_cellular_radio\": false, \"has_satellite_link\": false, \"coord\": [50.0, 95.0], \"id\": \"unit_1\"}], \"links\": []}",
    "{\"directed\": false, \"multigraph\": false, \"graph\": {}, \"nodes\": [{\"has_standard_radio\": false, \"has_cellular_radio\": false, \"has_satellite_link\": false, \"coord\": [50.0, 95.0], \"id\": \"unit_1\"}], \"links\": []}",
    "{\"directed\": false, \"multigraph\": false, \"graph\": {}, \"nodes\": [{\"has_standard_radio\": false, \"has_cellular_radio\": false, \"has_satellite_link\": false, \"coord\": [50.0, 95.0], \"id\": \"unit_1\"}], \"links\": []}",
    "{\"directed\": false, \"multigraph\": false, \"graph\": {}, \"nodes\": [{\"has_standard_radio\": false, \"has_cellular_radio\": false, \"has_satellite_link\": false, \"coord\": [50.0, 95.0], \"id\": \"unit_1\"}], \"links\": []}",
    "{\"directed\": false, \"multigraph\": false, \"graph\": {}, \"nodes\": [{\"has_standard_radio\": false, \"has_cellular_radio\": false, \"has_satellite_link\": false, \"coord\": [50.0, 95.0], \"id\": \"unit_1\"}], \"links\": []}",
    "{\"directed\": false, \"multigraph\": false, \"graph\": {}, \"nodes\": [{\"has_standard_radio\": false, \"has_cellular_radio\": false, \"has_satellite_link\": false, \"coord\": [50.0, 95.0], \"id\": \"unit_1\"}], \"links\": []}",
    "{\"directed\": false, \"multigraph\": false, \"graph\": {}, \"nodes\": [{\"has_standard_radio\": false, \"has_cellular_radio\": false, \"has_satellite_link\": false, \"coord\": [50.0, 95.0], \"id\": \"unit_1\"}], \"links\": []}",
    "{\"directed\": false, \"multigraph\": false, \"graph\": {}, \"nodes\": [{\"has_standard_radio\": false, \"has_cellular_radio\": false, \"has_satellite_link\": false, \"coord\": [50.0, 95.0], \"id\": \"unit_1\"}], \"links\": []}",
    "{\"directed\": false, \"multigraph\": false, \"graph\": {}, \"nodes\": [{\"has_standard_radio\": false, \"has_cellular_radio\": false, \"has_satellite_link\": false, \"coord\": [50.0, 95.0], \"id\": \"unit_1\"}], \"links\": []}",
    "{\"directed\": false, \"multigraph\": false, \"graph\": {}, \"nodes\": [{\"has_standard_radio\": false, \"has_cellular_radio\": false, \"has_satellite_link\": false, \"coord\": [50.0, 95.0], \"id\": \"unit_1\"}], \"links\": []}",
    "{\"directed\": false, \"multigraph\": false, \"graph\": {}, \"nodes\": [{\"has_standard_radio\": false, \"has_cellular_radio\": false, \"has_satellite_link\": false, \"coord\": [50.0, 95.0], \"id\": \"unit_1\"}], \"links\": []}",
    "{\"directed\": false, \"multigraph\": false, \"graph\": {}, \"nodes\": [{\"has_standard_radio\": false, \"has_cellular_radio\": false, \"has_satellite_link\": false, \"coord\": [50.0, 95.0], \"id\": \"unit_1\"}], \"links\": []}",
    "{\"directed\": false, \"multigraph\": false, \"graph\": {}, \"nodes\": [{\"has_standard_radio\": false, \"has_cellular_radio\": false, \"has_satellite_link\": false, \"coord\": [50.0, 95.0], \"id\": \"unit_1\"}], \"links\": []}",
    "{\"directed\": false, \"multigraph\": false, \"graph\": {}, \"nodes\": [{\"has_standard_radio\": false, \"has_cellular_radio\": false, \"has_satellite_link\": false, \"coord\": [50.0, 95.0], \"id\": \"unit_1\"}], \"links\": []}",
    "{\"directed\": false, \"multigraph\": false, \"graph\": {}, \"nodes\": [{\"has_standard_radio\": false, \"has_cellular_radio\": false, \"has_satellite_link\": false, \"coord\": [50.0, 95.0], \"id\": \"unit_1\"}], \"links\": []}",
    "{\"directed\": false, \"multigraph\": false, \"graph\": {}, \"nodes\": [{\"has_standard_radio\": false, \"has_cellular_radio\": false, \"has_satellite_link\": false, \"coord\": [50.0, 95.0], \"id\": \"unit_1\"}], \"links\": []}",
    "{\"directed\": false, \"multigraph\": false, \"graph\": {}, \"nodes\": [{\"has_standard_radio\": false, \"has_cellular_radio\": false, \"has_satellite_link\": false, \"coord\": [50.0, 95.0], \"id\": \"unit_1\"}], \"links\": []}",
    "{\"directed\": false, \"multigraph\": false, \"graph\": {}, \"nodes\": [{\"has_standard_radio\": false, \"has_cellular_radio\": false, \"has_satellite_link\": false, \"coord\": [50.0, 95.0], \"id\": \"unit_1\"}], \"links\": []}",
    "{\"directed\": false, \"multigraph\": false, \"graph\": {}, \"nodes\": [{\"has_standard_radio\": false, \"has_cellular_radio\": false, \"has_satellite_link\": false, \"coord\": [50.0, 95.0], \"id\": \"unit_1\"}], \"links\": []}",
    "{\"directed\": false, \"multigraph\": false, \"graph\": {}, \"nodes\": [{\"has_standard_radio\": false, \"has_cellular_radio\": false, \"has_satellite_link\": false, \"coord\": [50.0, 95.0], \"id\": \"unit_1\"}], \"links\": []}",
    "{\"directed\": false, \"multigraph\": false, \"graph\": {}, \"nodes\": [{\"has_standard_radio\": false, \"has_cellular_radio\": false, \"has_satellite_link\": false, \"coord\": [50.0, 95.0], \"id\": \"unit_1\"}], \"links\": []}",
    "{\"directed\": false, \"multigraph\": false, \"graph\": {}, \"nodes\": [{\"has_standard_radio\": false, \"has_cellular_radio\": false, \"has_satellite_link\": false, \"coord\": [50.0, 95.0], \"id\": \"unit_1\"}], \"links\": []}",
    "{\"directed\": false, \"multigraph\": false, \"graph\": {}, \"nodes\": [{\"has_standard_radio\": false, \"has_cellular_radio\": false, \"has_satellite_link\": false, \"coord\": [50.0, 95.0], \"id\": \"unit_1\"}], \"links\": []}",
    "{\"directed\": false, \"multigraph\": false, \"graph\": {}, \"nodes\": [{\"has_standard_radio\": false, \"has_cellular_radio\": false, \"has_satellite_link\": false, \"coord\": [50.0, 95.0], \"id\": \"unit_1\"}], \"links\": []}",
    "{\"directed\": false, \"multigraph\": false, \"graph\": {}, \"nodes\": [{\"has_standard_radio\": false, \"has_cellular_radio\": false, \"has_satellite_link\": false, \"coord\": [50.0, 95.0], \"id\": \"unit_1\"}], \"links\": []}",
    "{\"directed\": false, \"multigraph\": false, \"graph\": {}, \"nodes\": [{\"has_standard_radio\": false, \"has_cellular_radio\": false, \"has_satellite_link\": false, \"coord\": [50.0, 95.0], \"id\": \"unit_1\"}], \"links\": []}",
    "{\"directed\": false, \"multigraph\": false, \"graph\": {}, \"nodes\": [{\"has_standard_radio\": false, \"has_cellular_radio\": false, \"has_satellite_link\": false, \"coord\": [50.0, 95.0], \"id\": \"unit_1\"}], \"links\": []}",
    "{\"directed\": false, \"multigraph\": false, \"graph\": {}, \"nodes\": [{\"has_standard_radio\": false, \"has_cellular_radio\": false, \"has_satellite_link\": false, \"coord\": [50.0, 95.0], \"id\": \"unit_1\"}], \"links\": []}",
    "{\"directed\": false, \"multigraph\": false, \"graph\": {}, \"nodes\": [{\"has_standard_radio\": false, \"has_cellular_radio\": false, \"has_satellite_link\": false, \"coord\": [50.0, 95.0], \"id\": \"unit_1\"}], \"links\": []}",
    "{\"directed\": false, \"multigraph\": false, \"graph\": {}, \"nodes\": [{\"has_standard_radio\": false, \"has_cellular_radio\": false, \"has_satellite_link\": false, \"coord\": [50.0, 95.0], \"id\": \"unit_1\"}], \"links\": []}",
    "{\"directed\": false, \"multigraph\": false, \"graph\": {}, \"nodes\": [{\"has_standard_radio\": false, \"has_cellular_radio\": false, \"has_satellite_link\": false, \"coord\": [50.0, 95.0], \"id\": \"unit_1\"}], \"links\": []}",
    "{\"directed\": false, \"multigraph\": false, \"graph\": {}, \"nodes\": [{\"has_standard_radio\": false, \"has_cellular_radio\": false, \"has_satellite_link\": false, \"coord\": [50.0, 95.0], \"id\": \"unit_1\"}], \"links\": []}",
    "{\"directed\": false, \"multigraph\": false, \"graph\": {}, \"nodes\": [{\"has_standard_radio\": false, \"has_cellular_radio\": false, \"has_satellite_link\": false, \"coord\": [50.0, 95.0], \"id\": \"unit_1\"}], \"links\": []}",
    "{\"directed\": false, \"multigraph\": false, \"graph\": {}, \"nodes\": [{\"has_standard_radio\": false, \"has_cellular_radio\": false, \"has_satellite_link\": false, \"coord\": [50.0, 95.0], \"id\": \"unit_1\"}], \"links\": []}",
    "{\"directed\": false, \"multigraph\": false, \"graph\": {}, \"nodes\": [{\"has_standard_radio\": false, \"has_cellular_radio\": false, \"has_satellite_link\": false, \"coord\": [50.0, 95.0], \"id\": \"unit_1\"}], \"links\": []}",
    "{\"directed\": false, \"multigraph\": false, \"graph\": {}, \"nodes\": [{\"has_standard_radio\": false, \"has_cellular_radio\": false, \"has_satellite_link\": false, \"coord\": [50.0, 95.0], \"id\": \"unit_1\"}], \"links\": []}",
    "{\"directed\": false, \"multigraph\": false, \"graph\": {}, \"nodes\": [{\"has_standard_radio\": false, \"has_cellular_radio\": false, \"has_satellite_link\": false, \"coord\": [50.0, 95.0], \"id\": \"unit_1\"}], \"links\": []}",
    "{\"directed\": false, \"multigraph\": false, \"graph\": {}, \"nodes\": [{\"has_standard_radio\": false, \"has_cellular_radio\": false, \"has_satellite_link\": false, \"coord\": [50.0, 95.0], \"id\": \"unit_1\"}], \"links\": []}",
    "{\"directed\": false, \"multigraph\": false, \"graph\": {}, \"nodes\": [{\"has_standard_radio\": false, \"has_cellular_radio\": false, \"has_satellite_link\": false, \"coord\": [50.0, 95.0], \"id\": \"unit_1\"}], \"links\": []}",
    "{\"directed\": false, \"multigraph\": false, \"graph\": {}, \"nodes\": [{\"has_standard_radio\": false, \"has_cellular_radio\": false, \"has_satellite_link\": false, \"coord\": [50.0, 95.0], \"id\": \"unit_1\"}], \"links\": []}",
    "{\"directed\": false, \"multigraph\": false, \"graph\": {}, \"nodes\": [{\"has_standard_radio\": false, \"has_cellular_radio\": false, \"has_satellite_link\": false, \"coord\": [50.0, 95.0], \"id\": \"unit_1\"}], \"links\": []}",
    "{\"directed\": false, \"multigraph\": false, \"graph\": {}, \"nodes\": [{\"has_standard_radio\": false, \"has_cellular_radio\": false, \"has_satellite_link\": false, \"coord\": [50.0, 95.0], \"id\": \"unit_1\"}], \"links\": []}",
    "{\"directed\": false, \"multigraph\": false, \"graph\": {}, \"nodes\": [{\"has_standard_radio\": false, \"has_cellular_radio\": false, \"has_satellite_link\": false, \"coord\": [50.0, 95.0], \"id\": \"unit_1\"}], \"links\": []}",
    "{\"directed\": false, \"multigraph\": false, \"graph\": {}, \"nodes\": [{\"has_standard_radio\": false, \"has_cellular_radio\": false, \"has_satellite_link\": false, \"coord\": [50.0, 95.0], \"id\": \"unit_1\"}], \"links\": []}",
    "{\"directed\": false, \"multigraph\": false, \"graph\": {}, \"nodes\": [{\"has_standard_radio\": false, \"has_cellular_radio\": false, \"has_satellite_link\": false, \"coord\": [50.0, 95.0], \"id\": \"unit_1\"}], \"links\": []}",
    "{\"directed\": false, \"multigraph\": false, \"graph\": {}, \"nodes\": [{\"has_standard_radio\": false, \"has_cellular_radio\": false, \"has_satellite_link\": false, \"coord\": [50.0, 95.0], \"id\": \"unit_1\"}], \"links\": []}",
    "{\"directed\": false, \"multigraph\": false, \"graph\": {}, \"nodes\": [{\"has_standard_radio\": false, \"has_cellular_radio\": false, \"has_satellite_link\": false, \"coord\": [50.0, 95.0], \"id\": \"unit_1\"}], \"links\": []}",
    "{\"directed\": false, \"multigraph\": false, \"graph\": {}, \"nodes\": [{\"has_standard_radio\": false, \"has_cellular_radio\": false, \"has_satellite_link\": false, \"coord\": [50.0, 95.0], \"id\": \"unit_1\"}], \"links\": []}",
    "{\"directed\": false, \"multigraph\": false, \"graph\": {}, \"nodes\": [{\"has_standard_radio\": false, \"has_cellular_radio\": false, \"has_satellite_link\": false, \"coord\": [50.0, 95.0], \"id\": \"unit_1\"}], \"links\": []}",
    "{\"directed\": false, \"multigraph\": false, \"graph\": {}, \"nodes\": [{\"has_standard_radio\": false, \"has_cellular_radio\": false, \"has_satellite_link\": false, \"coord\": [50.0, 95.0], \"id\": \"unit_1\"}], \"links\": []}",
    "{\"directed\": false, \"multigraph\": false, \"graph\": {}, \"nodes\": [{\"has_standard_radio\": false, \"has_cellular_radio\": false, \"has_satellite_link\": false, \"coord\": [50.0, 95.0], \"id\": \"unit_1\"}], \"links\": []}",
    "{\"directed\": false, \"multigraph\": false, \"graph\": {}, \"nodes\": [{\"has_standard_radio\": false, \"has_cellular_radio\": false, \"has_satellite_link\": false, \"coord\": [50.0, 95.0], \"id\": \"unit_1\"}], \"links\": []}",
    "{\"directed\": false, \"multigraph\": false, \"graph\": {}, \"nodes\": [{\"has_standard_radio\": false, \"has_cellular_radio\": false, \"has_satellite_link\": false, \"coord\": [50.0, 95.0], \"id\": \"unit_1\"}], \"links\": []}",
    "{\"directed\": false, \"multigraph\": false, \"graph\": {}, \"nodes\": [{\"has_standard_radio\": false, \"has_cellular_radio\": false, \"has_satellite_link\": false, \"coord\": [50.0, 95.0], \"id\": \"unit_1\"}], \"links\": []}",
    "{\"directed\": false, \"multigraph\": false, \"graph\": {}, \"nodes\": [{\"has_standard_radio\": false, \"has_cellular_radio\": false, \"has_satellite_link\": false, \"coord\": [50.0, 95.0], \"id\": \"unit_1\"}], \"links\": []}",
    "{\"directed\": false, \"multigraph\": false, \"graph\": {}, \"nodes\": [{\"has_standard_radio\": false, \"has_cellular_radio\": false, \"has_satellite_link\": false, \"coord\": [50.0, 95.0], \"id\": \"unit_1\"}], \"links\": []}",
    "{\"directed\": false, \"multigraph\": false, \"graph\": {}, \"nodes\": [{\"has_standard_radio\": false, \"has_cellular_radio\": false, \"has_satellite_link\": false, \"coord\": [50.0, 95.0], \"id\": \"unit_1\"}], \"links\": []}",
    "{\"directed\": false, \"multigraph\": false, \"graph\": {}, \"nodes\": [{\"has_standard_radio\": false, \"has_cellular_radio\": false, \"has_satellite_link\": false, \"coord\": [50.0, 95.0], \"id\": \"unit_1\"}], \"links\": []}",
    "{\"directed\": false, \"multigraph\": false, \"graph\": {}, \"nodes\": [{\"has_standard_radio\": false, \"has_cellular_radio\": false, \"has_satellite_link\": false, \"coord\": [50.0, 95.0], \"id\": \"unit_1\"}], \"links\": []}",
    "{\"directed\": false, \"multigraph\": false, \"graph\": {}, \"nodes\": [{\"has_standard_radio\": false, \"has_cellular_radio\": false, \"has_satellite_link\": false, \"coord\": [50.0, 95.0], \"id\": \"unit_1\"}], \"links\": []}",
    "{\"directed\": false, \"multigraph\": false, \"graph\": {}, \"nodes\": [{\"has_standard_radio\": false, \"has_cellular_radio\": false, \"has_satellite_link\": false, \"coord\": [50.0, 95.0], \"id\": \"unit_1\"}], \"links\": []}",
    "{\"directed\": false, \"multigraph\": false, \"graph\": {}, \"nodes\": [{\"has_standard_radio\": false, \"has_cellular_radio\": false, \"has_satellite_link\": false, \"coord\": [50.0, 95.0], \"id\": \"unit_1\"}], \"links\": []}",
    "{\"directed\": false, \"multigraph\": false, \"graph\": {}, \"nodes\": [{\"has_standard_radio\": false, \"has_cellular_radio\": false, \"has_satellite_link\": false, \"coord\": [50.0, 95.0], \"id\": \"unit_1\"}], \"links\": []}",
    "{\"directed\": false, \"multigraph\": false, \"graph\": {}, \"nodes\": [{\"has_standard_radio\": false, \"has_cellular_radio\": false, \"has_satellite_link\": false, \"coord\": [50.0, 95.0], \"id\": \"unit_1\"}], \"links\": []}",
    "{\"directed\": false, \"multigraph\": false, \"graph\": {}, \"nodes\": [{\"has_standard_radio\": false, \"has_cellular_radio\": false, \"has_satellite_link\": false, \"coord\": [50.0, 95.0], \"id\": \"unit_1\"}], \"links\": []}",
    "{\"directed\": false, \"multigraph\": false, \"graph\": {}, \"nodes\": [{\"has_standard_radio\": false, \"has_cellular_radio\": false, \"has_satellite_link\": false, \"coord\": [50.0, 95.0], \"id\": \"unit_1\"}], \"links\": []}",
    "{\"directed\": false, \"multigraph\": false, \"graph\": {}, \"nodes\": [{\"has_standard_radio\": false, \"has_cellular_radio\": false, \"has_satellite_link\": false, \"coord\": [50.0, 95.0], \"id\": \"unit_1\"}], \"links\": []}",
    "{\"directed\": false, \"multigraph\": false, \"graph\": {}, \"nodes\": [{\"has_standard_radio\": false, \"has_cellular_radio\": false, \"has_satellite_link\": false, \"coord\": [50.0, 95.0], \"id\": \"unit_1\"}], \"links\": []}",
    "{\"directed\": false, \"multigraph\": false, \"graph\": {}, \"nodes\": [{\"has_standard_radio\": false, \"has_cellular_radio\": false, \"has_satellite_link\": false, \"coord\": [50.0, 95.0], \"id\": \"unit_1\"}], \"links\": []}",
    "{\"directed\": false, \"multigraph\": false, \"graph\": {}, \"nodes\": [{\"has_standard_radio\": false, \"has_cellular_radio\": false, \"has_satellite_link\": false, \"coord\": [50.0, 95.0], \"id\": \"unit_1\"}], \"links\": []}",
    "{\"directed\": false, \"multigraph\": false, \"graph\": {}, \"nodes\": [{\"has_standard_radio\": false, \"has_cellular_radio\": false, \"has_satellite_link\": false, \"coord\": [50.0, 95.0], \"id\": \"unit_1\"}], \"links\": []}",
    "{\"directed\": false, \"multigraph\": false, \"graph\": {}, \"nodes\": [{\"has_standard_radio\": false, \"has_cellular_radio\": false, \"has_satellite_link\": false, \"coord\": [50.0, 95.0], \"id\": \"unit_1\"}], \"links\": []}",
    "{\"directed\": false, \"multigraph\": false, \"graph\": {}, \"nodes\": [{\"has_standard_radio\": false, \"has_cellular_radio\": false, \"has_satellite_link\": false, \"coord\": [50.0, 95.0], \"id\": \"unit_1\"}], \"links\": []}",
    "{\"directed\": false, \"multigraph\": false, \"graph\": {}, \"nodes\": [{\"has_standard_radio\": false, \"has_cellular_radio\": false, \"has_satellite_link\": false, \"coord\": [50.0, 95.0], \"id\": \"unit_1\"}], \"links\": []}",
    "{\"directed\": false, \"multigraph\": false, \"graph\": {}, \"nodes\": [{\"has_standard_radio\": false, \"has_cellular_radio\": false, \"has_satellite_link\": false, \"coord\": [50.0, 95.0], \"id\": \"unit_1\"}], \"links\": []}",
    "{\"directed\": false, \"multigraph\": false, \"graph\": {}, \"nodes\": [{\"has_standard_radio\": false, \"has_cellular_radio\": false, \"has_satellite_link\": false, \"coord\": [50.0, 95.0], \"id\": \"unit_1\"}], \"links\": []}",
    "{\"directed\": false, \"multigraph\": false, \"graph\": {}, \"nodes\": [{\"has_standard_radio\": false, \"has_cellular_radio\": false, \"has_satellite_link\": false, \"coord\": [50.0, 95.0], \"id\": \"unit_1\"}], \"links\": []}",
    "{\"directed\": false, \"multigraph\": false, \"graph\": {}, \"nodes\": [{\"has_standard_radio\": false, \"has_cellular_radio\": false, \"has_satellite_link\": false, \"coord\": [50.0, 95.0], \"id\": \"unit_1\"}], \"links\": []}",
    "{\"directed\": false, \"multigraph\": false, \"graph\": {}, \"nodes\": [{\"has_standard_radio\": false, \"has_cellular_radio\": false, \"has_satellite_link\": false, \"coord\": [50.0, 95.0], \"id\": \"unit_1\"}], \"links\": []}",
    "{\"directed\": false, \"multigraph\": false, \"graph\": {}, \"nodes\": [{\"has_standard_radio\": false, \"has_cellular_radio\": false, \"has_satellite_link\": false, \"coord\": [50.0, 95.0], \"id\": \"unit_1\"}], \"links\": []}",
    "{\"directed\": false, \"multigraph\": false, \"graph\": {}, \"nodes\": [{\"has_standard_radio\": false, \"has_cellular_radio\": false, \"has_satellite_link\": false, \"coord\": [50.0, 95.0], \"id\": \"unit_1\"}], \"links\": []}",
    "{\"directed\": false, \"multigraph\": false, \"graph\": {}, \"nodes\": [{\"has_standard_radio\": false, \"has_cellular_radio\": false, \"has_satellite_link\": false, \"coord\": [50.0, 95.0], \"id\": \"unit_1\"}], \"links\": []}",
    "{\"directed\": false, \"multigraph\": false, \"graph\": {}, \"nodes\": [{\"has_standard_radio\": false, \"has_cellular_radio\": false, \"has_satellite_link\": false, \"coord\": [50.0, 95.0], \"id\": \"unit_1\"}], \"links\": []}",
    "{\"directed\": false, \"multigraph\": false, \"graph\": {}, \"nodes\": [{\"has_standard_radio\": false, \"has_cellular_radio\": false, \"has_satellite_link\": false, \"coord\": [50.0, 95.0], \"id\": \"unit_1\"}], \"links\": []}",
    "{\"directed\": false, \"multigraph\": false, \"graph\": {}, \"nodes\": [{\"has_standard_radio\": false, \"has_cellular_radio\": false, \"has_satellite_link\": false, \"coord\": [50.0, 95.0], \"id\": \"unit_1\"}], \"links\": []}",
    "{\"directed\": false, \"multigraph\": false, \"graph\": {}, \"nodes\": [{\"has_standard_radio\": false, \"has_cellular_radio\": false, \"has_satellite_link\": false, \"coord\": [50.0, 95.0], \"id\": \"unit_1\"}], \"links\": []}",
    "{\"directed\": false, \"multigraph\": false, \"graph\": {}, \"nodes\": [{\"has_standard_radio\": false, \"has_cellular_radio\": false, \"has_satellite_link\": false, \"coord\": [50.0, 95.0], \"id\": \"unit_1\"}], \"links\": []}",
    "{\"directed\": false, \"multigraph\": false, \"graph\": {}, \"nodes\": [{\"has_standard_radio\": false, \"has_cellular_radio\": false, \"has_satellite_link\": false, \"coord\": [50.0, 95.0], \"id\": \"unit_1\"}], \"links\": []}",
    "{\"directed\": false, \"multigraph\": false, \"graph\": {}, \"nodes\": [{\"has_standard_radio\": false, \"has_cellular_radio\": false, \"has_satellite_link\": false, \"coord\": [50.0, 95.0], \"id\": \"unit_1\"}], \"links\": []}",
    "{\"directed\": false, \"multigraph\": false, \"graph\": {}, \"nodes\": [{\"has_standard_radio\": false, \"has_cellular_radio\": false, \"has_satellite_link\": false, \"coord\": [50.0, 95.0], \"id\": \"unit_1\"}], \"links\": []}",
    "{\"directed\": false, \"multigraph\": false, \"graph\": {}, \"nodes\": [{\"has_standard_radio\": false, \"has_cellular_radio\": false, \"has_satellite_link\": false, \"coord\": [50.0, 95.0], \"id\": \"unit_1\"}], \"links\": []}",
    "{\"directed\": false, \"multigraph\": false, \"graph\": {}, \"nodes\": [{\"has_standard_radio\": false, \"has_cellular_radio\": false, \"has_satellite_link\": false, \"coord\": [50.0, 95.0], \"id\": \"unit_1\"}], \"links\": []}",
    "{\"directed\": false, \"multigraph\": false, \"graph\": {}, \"nodes\": [{\"has_standard_radio\": false, \"has_cellular_radio\": false, \"has_satellite_link\": false, \"coord\": [50.0, 95.0], \"id\": \"unit_1\"}], \"links\": []}",
    "{\"directed\": false, \"multigraph\": false, \"graph\": {}, \"nodes\": [{\"has_standard_radio\": false, \"has_cellular_radio\": false, \"has_satellite_link\": false, \"coord\": [50.0, 95.0], \"id\": \"unit_1\"}], \"links\": []}",
    "{\"directed\": false, \"multigraph\": false, \"graph\": {}, \"nodes\": [{\"has_standard_radio\": false, \"has_cellular_radio\": false, \"has_satellite_link\": false, \"coord\": [50.0, 95.0], \"id\": \"unit_1\"}], \"links\": []}",
    "{\"directed\": false, \"multigraph\": false, \"graph\": {}, \"nodes\": [{\"has_standard_radio\": false, \"has_cellular_radio\": false, \"has_satellite_link\": false, \"coord\": [50.0, 95.0], \"id\": \"unit_1\"}], \"links\": []}",
    "{\"directed\": false, \"multigraph\": false, \"graph\": {}, \"nodes\": [{\"has_standard_radio\": false, \"has_cellular_radio\": false, \"has_satellite_link\": false, \"coord\": [50.0, 95.0], \"id\": \"unit_1\"}], \"links\": []}",
    "{\"directed\": false, \"multigraph\": false, \"graph\": {}, \"nodes\": [{\"has_standard_radio\": false, \"has_cellular_radio\": false, \"has_satellite_link\": false, \"coord\": [50.0, 95.0], \"id\": \"unit_1\"}], \"links\": []}",
    "{\"directed\": false, \"multigraph\": false, \"graph\": {}, \"nodes\": [{\"has_standard_radio\": false, \"has_cellular_radio\": false, \"has_satellite_link\": false, \"coord\": [50.0, 95.0], \"id\": \"unit_1\"}], \"links\": []}",
    "{\"directed\": false, \"multigraph\": false, \"graph\": {}, \"nodes\": [{\"has_standard_radio\": false, \"has_cellular_radio\": false, \"has_satellite_link\": false, \"coord\": [50.0, 95.0], \"id\": \"unit_1\"}], \"links\": []}",
    "{\"directed\": false, \"multigraph\": false, \"graph\": {}, \"nodes\": [{\"has_standard_radio\": false, \"has_cellular_radio\": false, \"has_satellite_link\": false, \"coord\": [50.0, 95.0], \"id\": \"unit_1\"}], \"links\": []}",
    "{\"directed\": false, \"multigraph\": false, \"graph\": {}, \"nodes\": [{\"has_standard_radio\": false, \"has_cellular_radio\": false, \"has_satellite_link\": false, \"coord\": [50.0, 95.0], \"id\": \"unit_1\"}], \"links\": []}",
    "{\"directed\": false, \"multigraph\": false, \"graph\": {}, \"nodes\": [{\"has_standard_radio\": false, \"has_cellular_radio\": false, \"has_satellite_link\": false, \"coord\": [50.0, 95.0], \"id\": \"unit_1\"}], \"links\": []}",
    "{\"directed\": false, \"multigraph\": false, \"graph\": {}, \"nodes\": [{\"has_standard_radio\": false, \"has_cellular_radio\": false, \"has_satellite_link\": false, \"coord\": [50.0, 95.0], \"id\": \"unit_1\"}], \"links\": []}",
    "{\"directed\": false, \"multigraph\": false, \"graph\": {}, \"nodes\": [{\"has_standard_radio\": false, \"has_cellular_radio\": false, \"has_satellite_link\": false, \"coord\": [50.0, 95.0], \"id\": \"unit_1\"}], \"links\": []}",
    "{\"directed\": false, \"multigraph\": false, \"graph\": {}, \"nodes\": [{\"has_standard_radio\": false, \"has_cellular_radio\": false, \"has_satellite_link\": false, \"coord\": [50.0, 95.0], \"id\": \"unit_1\"}], \"links\": []}",
    "{\"directed\": false, \"multigraph\": false, \"graph\": {}, \"nodes\": [{\"has_standard_radio\": false, \"has_cellular_radio\": false, \"has_satellite_link\": false, \"coord\": [50.0, 95.0], \"id\": \"unit_1\"}], \"links\": []}",
    "{\"directed\": false, \"multigraph\": false, \"graph\": {}, \"nodes\": [{\"has_standard_radio\": false, \"has_cellular_radio\": false, \"has_satellite_link\": false, \"coord\": [50.0, 95.0], \"id\": \"unit_1\"}], \"links\": []}",
    "{\"directed\": false, \"multigraph\": false, \"graph\": {}, \"nodes\": [{\"has_standard_radio\": false, \"has_cellular_radio\": false, \"has_satellite_link\": false, \"coord\": [50.0, 95.0], \"id\": \"unit_1\"}], \"links\": []}",
    "{\"directed\": false, \"multigraph\": false, \"graph\": {}, \"nodes\": [{\"has_standard_radio\": false, \"has_cellular_radio\": false, \"has_satellite_link\": false, \"coord\": [50.0, 95.0], \"id\": \"unit_1\"}], \"links\": []}",
    "{\"directed\": false, \"multigraph\": false, \"graph\": {}, \"nodes\": [{\"has_standard_radio\": false, \"has_cellular_radio\": false, \"has_satellite_link\": false, \"coord\": [50.0, 95.0], \"id\": \"unit_1\"}], \"links\": []}",
    "{\"directed\": false, \"multigraph\": false, \"graph\": {}, \"nodes\": [{\"has_standard_radio\": false, \"has_cellular_radio\": false, \"has_satellite_link\": false, \"coord\": [50.0, 95.0], \"id\": \"unit_1\"}], \"links\": []}",
    "{\"directed\": false, \"multigraph\": false, \"graph\": {}, \"nodes\": [{\"has_standard_radio\": false, \"has_cellular_radio\": false, \"has_satellite_link\": false, \"coord\": [50.0, 95.0], \"id\": \"unit_1\"}], \"links\": []}",
    "{\"directed\": false, \"multigraph\": false, \"graph\": {}, \"nodes\": [{\"has_standard_radio\": false, \"has_cellular_radio\": false, \"has_satellite_link\": false, \"coord\": [50.0, 95.0], \"id\": \"unit_1\"}], \"links\": []}",
    "{\"directed\": false, \"multigraph\": false, \"graph\": {}, \"nodes\": [{\"has_standard_radio\": false, \"has_cellular_radio\": false, \"has_satellite_link\": false, \"coord\": [50.0, 95.0], \"id\": \"unit_1\"}], \"links\": []}",
    "{\"directed\": false, \"multigraph\": false, \"graph\": {}, \"nodes\": [{\"has_standard_radio\": false, \"has_cellular_radio\": false, \"has_satellite_link\": false, \"coord\": [50.0, 95.0], \"id\": \"unit_1\"}], \"links\": []}",
    "{\"directed\": false, \"multigraph\": false, \"graph\": {}, \"nodes\": [{\"has_standard_radio\": false, \"has_cellular_radio\": false, \"has_satellite_link\": false, \"coord\": [50.0, 95.0], \"id\": \"unit_1\"}], \"links\": []}",
    "{\"directed\": false, \"multigraph\": false, \"graph\": {}, \"nodes\": [{\"has_standard_radio\": false, \"has_cellular_radio\": false, \"has_satellite_link\": false, \"coord\": [50.0, 95.0], \"id\": \"unit_1\"}], \"links\": []}",
    "{\"directed\": false, \"multigraph\": false, \"graph\": {}, \"nodes\": [{\"has_standard_radio\": false, \"has_cellular_radio\": false, \"has_satellite_link\": false, \"coord\": [50.0, 95.0], \"id\": \"unit_1\"}], \"links\": []}",
    "{\"directed\": false, \"multigraph\": false, \"graph\": {}, \"nodes\": [{\"has_standard_radio\": false, \"has_cellular_radio\": false, \"has_satellite_link\": false, \"coord\": [50.0, 95.0], \"id\": \"unit_1\"}], \"links\": []}",
    "{\"directed\": false, \"multigraph\": false, \"graph\": {}, \"nodes\": [{\"has_standard_radio\": false, \"has_cellular_radio\": false, \"has_satellite_link\": false, \"coord\": [50.0, 95.0], \"id\": \"unit_1\"}], \"links\": []}",
    "{\"directed\": false, \"multigraph\": false, \"graph\": {}, \"nodes\": [{\"has_standard_radio\": false, \"has_cellular_radio\": false, \"has_satellite_link\": false, \"coord\": [50.0, 95.0], \"id\": \"unit_1\"}], \"links\": []}",
    "{\"directed\": false, \"multigraph\": false, \"graph\": {}, \"nodes\": [{\"has_standard_radio\": false, \"has_cellular_radio\": false, \"has_satellite_link\": false, \"coord\": [50.0, 95.0], \"id\": \"unit_1\"}], \"links\": []}",
    "{\"directed\": false, \"multigraph\": false, \"graph\": {}, \"nodes\": [{\"has_standard_radio\": false, \"has_cellular_radio\": false, \"has_satellite_link\": false, \"coord\": [50.0, 95.0], \"id\": \"unit_1\"}], \"links\": []}",
    "{\"directed\": false, \"multigraph\": false, \"graph\": {}, \"nodes\": [{\"has_standard_radio\": false, \"has_cellular_radio\": false, \"has_satellite_link\": false, \"coord\": [50.0, 95.0], \"id\": \"unit_1\"}], \"links\": []}",
    "{\"directed\": false, \"multigraph\": false, \"graph\": {}, \"nodes\": [{\"has_standard_radio\": false, \"has_cellular_radio\": false, \"has_satellite_link\": false, \"coord\": [50.0, 95.0], \"id\": \"unit_1\"}], \"links\": []}",
    "{\"directed\": false, \"multigraph\": false, \"graph\": {}, \"nodes\": [{\"has_standard_radio\": false, \"has_cellular_radio\": false, \"has_satellite_link\": false, \"coord\": [50.0, 95.0], \"id\": \"unit_1\"}], \"links\": []}",
    "{\"directed\": false, \"multigraph\": false, \"graph\": {}, \"nodes\": [{\"has_standard_radio\": false, \"has_cellular_radio\": false, \"has_satellite_link\": false, \"coord\": [50.0, 95.0], \"id\": \"unit_1\"}], \"links\": []}",
    "{\"directed\": false, \"multigraph\": false, \"graph\": {}, \"nodes\": [{\"has_standard_radio\": false, \"has_cellular_radio\": false, \"has_satellite_link\": false, \"coord\": [50.0, 95.0], \"id\": \"unit_1\"}], \"links\": []}",
    "{\"directed\": false, \"multigraph\": false, \"graph\": {}, \"nodes\": [{\"has_standard_radio\": false, \"has_cellular_radio\": false, \"has_satellite_link\": false, \"coord\": [50.0, 95.0], \"id\": \"unit_1\"}], \"links\": []}",
    "{\"directed\": false, \"multigraph\": false, \"graph\": {}, \"nodes\": [{\"has_standard_radio\": false, \"has_cellular_radio\": false, \"has_satellite_link\": false, \"coord\": [50.0, 95.0], \"id\": \"unit_1\"}], \"links\": []}",
    "{\"directed\": false, \"multigraph\": false, \"graph\": {}, \"nodes\": [{\"has_standard_radio\": false, \"has_cellular_radio\": false, \"has_satellite_link\": false, \"coord\": [50.0, 95.0], \"id\": \"unit_1\"}], \"links\": []}",
    "{\"directed\": false, \"multigraph\": false, \"graph\": {}, \"nodes\": [{\"has_standard_radio\": false, \"has_cellular_radio\": false, \"has_satellite_link\": false, \"coord\": [50.0, 95.0], \"id\": \"unit_1\"}], \"links\": []}",
    "{\"directed\": false, \"multigraph\": false, \"graph\": {}, \"nodes\": [{\"has_standard_radio\": false, \"has_cellular_radio\": false, \"has_satellite_link\": false, \"coord\": [50.0, 95.0], \"id\": \"unit_1\"}], \"links\": []}",
    "{\"directed\": false, \"multigraph\": false, \"graph\": {}, \"nodes\": [{\"has_standard_radio\": false, \"has_cellular_radio\": false, \"has_satellite_link\": false, \"coord\": [50.0, 95.0], \"id\": \"unit_1\"}], \"links\": []}",
    "{\"directed\": false, \"multigraph\": false, \"graph\": {}, \"nodes\": [{\"has_standard_radio\": false, \"has_cellular_radio\": false, \"has_satellite_link\": false, \"coord\": [50.0, 95.0], \"id\": \"unit_1\"}], \"links\": []}",
    "{\"directed\": false, \"multigraph\": false, \"graph\": {}, \"nodes\": [{\"has_standard_radio\": false, \"has_cellular_radio\": false, \"has_satellite_link\": false, \"coord\": [50.0, 95.0], \"id\": \"unit_1\"}], \"links\": []}",
    "{\"directed\": false, \"multigraph\": false, \"graph\": {}, \"nodes\": [{\"has_standard_radio\": false, \"has_cellular_radio\": false, \"has_satellite_link\": false, \"coord\": [50.0, 95.0], \"id\": \"unit_1\"}], \"links\": []}",
    "{\"directed\": false, \"multigraph\": false, \"graph\": {}, \"nodes\": [{\"has_standard_radio\": false, \"has_cellular_radio\": false, \"has_satellite_link\": false, \"coord\": [50.0, 95.0], \"id\": \"unit_1\"}], \"links\": []}",
    "{\"directed\": false, \"multigraph\": false, \"graph\": {}, \"nodes\": [{\"has_standard_radio\": false, \"has_cellular_radio\": false, \"has_satellite_link\": false, \"coord\": [50.0, 95.0], \"id\": \"unit_1\"}], \"links\": []}",
    "{\"directed\": false, \"multigraph\": false, \"graph\": {}, \"nodes\": [{\"has_standard_radio\": false, \"has_cellular_radio\": false, \"has_satellite_link\": false, \"coord\": [50.0, 95.0], \"id\": \"unit_1\"}], \"links\": []}",
    "{\"directed\": false, \"multigraph\": false, \"graph\": {}, \"nodes\": [{\"has_standard_radio\": false, \"has_cellular_radio\": false, \"has_satellite_link\": false, \"coord\": [50.0, 95.0], \"id\": \"unit_1\"}], \"links\": []}",
    "{\"directed\": false, \"multigraph\": false, \"graph\": {}, \"nodes\": [{\"has_standard_radio\": false, \"has_cellular_radio\": false, \"has_satellite_link\": false, \"coord\": [50.0, 95.0], \"id\": \"unit_1\"}], \"links\": []}",
    "{\"directed\": false, \"multigraph\": false, \"graph\": {}, \"nodes\": [{\"has_standard_radio\": false, \"has_cellular_radio\": false, \"has_satellite_link\": false, \"coord\": [50.0, 95.0], \"id\": \"unit_1\"}], \"links\": []}",
    "{\"directed\": false, \"multigraph\": false, \"graph\": {}, \"nodes\": [{\"has_standard_radio\": false, \"has_cellular_radio\": false, \"has_satellite_link\": false, \"coord\": [50.0, 95.0], \"id\": \"unit_1\"}], \"links\": []}",
    "{\"directed\": false, \"multigraph\": false, \"graph\": {}, \"nodes\": [{\"has_standard_radio\": false, \"has_cellular_radio\": false, \"has_satellite_link\": false, \"coord\": [50.0, 95.0], \"id\": \"unit_1\"}], \"links\": []}",
    "{\"directed\": false, \"multigraph\": false, \"graph\": {}, \"nodes\": [{\"has_standard_radio\": false, \"has_cellular_radio\": false, \"has_satellite_link\": false, \"coord\": [50.0, 95.0], \"id\": \"unit_1\"}], \"links\": []}",
    "{\"directed\": false, \"multigraph\": false, \"graph\": {}, \"nodes\": [{\"has_standard_radio\": false, \"has_cellular_radio\": false, \"has_satellite_link\": false, \"coord\": [50.0, 95.0], \"id\": \"unit_1\"}], \"links\": []}",
    "{\"directed\": false, \"multigraph\": false, \"graph\": {}, \"nodes\": [{\"has_standard_radio\": false, \"has_cellular_radio\": false, \"has_satellite_link\": false, \"coord\": [50.0, 95.0], \"id\": \"unit_1\"}], \"links\": []}",
    "{\"directed\": false, \"multigraph\": false, \"graph\": {}, \"nodes\": [{\"has_standard_radio\": false, \"has_cellular_radio\": false, \"has_satellite_link\": false, \"coord\": [50.0, 95.0], \"id\": \"unit_1\"}], \"links\": []}",
    "{\"directed\": false, \"multigraph\": false, \"graph\": {}, \"nodes\": [{\"has_standard_radio\": false, \"has_cellular_radio\": false, \"has_satellite_link\": false, \"coord\": [50.0, 95.0], \"id\": \"unit_1\"}], \"links\": []}",
    "{\"directed\": false, \"multigraph\": false, \"graph\": {}, \"nodes\": [{\"has_standard_radio\": false, \"has_cellular_radio\": false, \"has_satellite_link\": false, \"coord\": [50.0, 95.0], \"id\": \"unit_1\"}], \"links\": []}",
    "{\"directed\": false, \"multigraph\": false, \"graph\": {}, \"nodes\": [{\"has_standard_radio\": false, \"has_cellular_radio\": false, \"has_satellite_link\": false, \"coord\": [50.0, 95.0], \"id\": \"unit_1\"}], \"links\": []}",
    "{\"directed\": false, \"multigraph\": false, \"graph\": {}, \"nodes\": [{\"has_standard_radio\": false, \"has_cellular_radio\": false, \"has_satellite_link\": false, \"coord\": [50.0, 95.0], \"id\": \"unit_1\"}], \"links\": []}",
    "{\"directed\": false, \"multigraph\": false, \"graph\": {}, \"nodes\": [{\"has_standard_radio\": false, \"has_cellular_radio\": false, \"has_satellite_link\": false, \"coord\": [50.0, 95.0], \"id\": \"unit_1\"}], \"links\": []}",
    "{\"directed\": false, \"multigraph\": false, \"graph\": {}, \"nodes\": [{\"has_standard_radio\": false, \"has_cellular_radio\": false, \"has_satellite_link\": false, \"coord\": [50.0, 95.0], \"id\": \"unit_1\"}], \"links\": []}",
    "{\"directed\": false, \"multigraph\": false, \"graph\": {}, \"nodes\": [{\"has_standard_radio\": false, \"has_cellular_radio\": false, \"has_satellite_link\": false, \"coord\": [50.0, 95.0], \"id\": \"unit_1\"}], \"links\": []}",
    "{\"directed\": false, \"multigraph\": false, \"graph\": {}, \"nodes\": [{\"has_standard_radio\": false, \"has_cellular_radio\": false, \"has_satellite_link\": false, \"coord\": [50.0, 95.0], \"id\": \"unit_1\"}], \"links\": []}",
    "{\"directed\": false, \"multigraph\": false, \"graph\": {}, \"nodes\": [{\"has_standard_radio\": false, \"has_cellular_radio\": false, \"has_satellite_link\": false, \"coord\": [50.0, 95.0], \"id\": \"unit_1\"}], \"links\": []}",
    "{\"directed\": false, \"multigraph\": false, \"graph\": {}, \"nodes\": [{\"has_standard_radio\": false, \"has_cellular_radio\": false, \"has_satellite_link\": false, \"coord\": [50.0, 95.0], \"id\": \"unit_1\"}], \"links\": []}",
    "{\"directed\": false, \"multigraph\": false, \"graph\": {}, \"nodes\": [{\"has_standard_radio\": false, \"has_cellular_radio\": false, \"has_satellite_link\": false, \"coord\": [50.0, 95.0], \"id\": \"unit_1\"}], \"links\": []}",
    "{\"directed\": false, \"multigraph\": false, \"graph\": {}, \"nodes\": [{\"has_standard_radio\": false, \"has_cellular_radio\": false, \"has_satellite_link\": false, \"coord\": [50.0, 95.0], \"id\": \"unit_1\"}], \"links\": []}",
    "{\"directed\": false, \"multigraph\": false, \"graph\": {}, \"nodes\": [{\"has_standard_radio\": false, \"has_cellular_radio\": false, \"has_satellite_link\": false, \"coord\": [50.0, 95.0], \"id\": \"unit_1\"}], \"links\": []}",
    "{\"directed\": false, \"multigraph\": false, \"graph\": {}, \"nodes\": [{\"has_standard_radio\": false, \"has_cellular_radio\": false, \"has_satellite_link\": false, \"coord\": [50.0, 95.0], \"id\": \"unit_1\"}], \"links\": []}",
    "{\"directed\": false, \"multigraph\": false, \"graph\": {}, \"nodes\": [{\"has_standard_radio\": false, \"has_cellular_radio\": false, \"has_satellite_link\": false, \"coord\": [50.0, 95.0], \"id\": \"unit_1\"}], \"links\": []}",
    "{\"directed\": false, \"multigraph\": false, \"graph\": {}, \"nodes\": [{\"has_standard_radio\": false, \"has_cellular_radio\": false, \"has_satellite_link\": false, \"coord\": [50.0, 95.0], \"id\": \"unit_1\"}], \"links\": []}",
    "{\"directed\": false, \"multigraph\": false, \"graph\": {}, \"nodes\": [{\"has_standard_radio\": false, \"has_cellular_radio\": false, \"has_satellite_link\": false, \"coord\": [50.0, 95.0], \"id\": \"unit_1\"}], \"links\": []}",
    "{\"directed\": false, \"multigraph\": false, \"graph\": {}, \"nodes\": [{\"has_standard_radio\": false, \"has_cellular_radio\": false, \"has_satellite_link\": false, \"coord\": [50.0, 95.0], \"id\": \"unit_1\"}], \"links\": []}",
    "{\"directed\": false, \"multigraph\": false, \"graph\": {}, \"nodes\": [{\"has_standard_radio\": false, \"has_cellular_radio\": false, \"has_satellite_link\": false, \"coord\": [50.0, 95.0], \"id\": \"unit_1\"}], \"links\": []}",
    "{\"directed\": false, \"multigraph\": false, \"graph\": {}, \"nodes\": [{\"has_standard_radio\": false, \"has_cellular_radio\": false, \"has_satellite_link\": false, \"coord\": [50.0, 95.0], \"id\": \"unit_1\"}], \"links\": []}",
    "{\"directed\": false, \"multigraph\": false, \"graph\": {}, \"nodes\": [{\"has_standard_radio\": false, \"has_cellular_radio\": false, \"has_satellite_link\": false, \"coord\": [50.0, 95.0], \"id\": \"unit_1\"}], \"links\": []}",
    "{\"directed\": false, \"multigraph\": false, \"graph\": {}, \"nodes\": [{\"has_standard_radio\": false, \"has_cellular_radio\": false, \"has_satellite_link\": false, \"coord\": [50.0, 95.0], \"id\": \"unit_1\"}], \"links\": []}",
    "{\"directed\": false, \"multigraph\": false, \"graph\": {}, \"nodes\": [{\"has_standard_radio\": false, \"has_cellular_radio\": false, \"has_satellite_link\": false, \"coord\": [50.0, 95.0], \"id\": \"unit_1\"}], \"links\": []}",
    "{\"directed\": false, \"multigraph\": false, \"graph\": {}, \"nodes\": [{\"has_standard_radio\": false, \"has_cellular_radio\": false, \"has_satellite_link\": false, \"coord\": [50.0, 95.0], \"id\": \"unit_1\"}], \"links\": []}",
    "{\"directed\": false, \"multigraph\": false, \"graph\": {}, \"nodes\": [{\"has_standard_radio\": false, \"has_cellular_radio\": false, \"has_satellite_link\": false, \"coord\": [50.0, 95.0], \"id\": \"unit_1\"}], \"links\": []}",
    "{\"directed\": false, \"multigraph\": false, \"graph\": {}, \"nodes\": [{\"has_standard_radio\": false, \"has_cellular_radio\": false, \"has_satellite_link\": false, \"coord\": [50.0, 95.0], \"id\": \"unit_1\"}], \"links\": []}",
    "{\"directed\": false, \"multigraph\": false, \"graph\": {}, \"nodes\": [{\"has_standard_radio\": false, \"has_cellular_radio\": false, \"has_satellite_link\": false, \"coord\": [50.0, 95.0], \"id\": \"unit_1\"}], \"links\": []}",
    "{\"directed\": false, \"multigraph\": false, \"graph\": {}, \"nodes\": [{\"has_standard_radio\": false, \"has_cellular_radio\": false, \"has_satellite_link\": false, \"coord\": [50.0, 95.0], \"id\": \"unit_1\"}], \"links\": []}",
    "{\"directed\": false, \"multigraph\": false, \"graph\": {}, \"nodes\": [{\"has_standard_radio\": false, \"has_cellular_radio\": false, \"has_satellite_link\": false, \"coord\": [50.0, 95.0], \"id\": \"unit_1\"}], \"links\": []}",
    "{\"directed\": false, \"multigraph\": false, \"graph\": {}, \"nodes\": [{\"has_standard_radio\": false, \"has_cellular_radio\": false, \"has_satellite_link\": false, \"coord\": [50.0, 95.0], \"id\": \"unit_1\"}], \"links\": []}",
    "{\"directed\": false, \"multigraph\": false, \"graph\": {}, \"nodes\": [{\"has_standard_radio\": false, \"has_cellular_radio\": false, \"has_satellite_link\": false, \"coord\": [50.0, 95.0], \"id\": \"unit_1\"}], \"links\": []}",
    "{\"directed\": false, \"multigraph\": false, \"graph\": {}, \"nodes\": [{\"has_standard_radio\": false, \"has_cellular_radio\": false, \"has_satellite_link\": false, \"coord\": [50.0, 95.0], \"id\": \"unit_1\"}], \"links\": []}",
    "{\"directed\": false, \"multigraph\": false, \"graph\": {}, \"nodes\": [{\"has_standard_radio\": false, \"has_cellular_radio\": false, \"has_satellite_link\": false, \"coord\": [50.0, 95.0], \"id\": \"unit_1\"}], \"links\": []}",
    "{\"directed\": false, \"multigraph\": false, \"graph\": {}, \"nodes\": [{\"has_standard_radio\": false, \"has_cellular_radio\": false, \"has_satellite_link\": false, \"coord\": [50.0, 95.0], \"id\": \"unit_1\"}], \"links\": []}",
    "{\"directed\": false, \"multigraph\": false, \"graph\": {}, \"nodes\": [{\"has_standard_radio\": false, \"has_cellular_radio\": false, \"has_satellite_link\": false, \"coord\": [50.0, 95.0], \"id\": \"unit_1\"}], \"links\": []}",
    "{\"directed\": false, \"multigraph\": false, \"graph\": {}, \"nodes\": [{\"has_standard_radio\": false, \"has_cellular_radio\": false, \"has_satellite_link\": false, \"coord\": [50.0, 95.0], \"id\": \"unit_1\"}], \"links\": []}",
    "{\"directed\": false, \"multigraph\": false, \"graph\": {}, \"nodes\": [{\"has_standard_radio\": false, \"has_cellular_radio\": false, \"has_satellite_link\": false, \"coord\": [50.0, 95.0], \"id\": \"unit_1\"}], \"links\": []}",
    "{\"directed\": false, \"multigraph\": false, \"graph\": {}, \"nodes\": [{\"has_standard_radio\": false, \"has_cellular_radio\": false, \"has_satellite_link\": false, \"coord\": [50.0, 95.0], \"id\": \"unit_1\"}], \"links\": []}",
    "{\"directed\": false, \"multigraph\": false, \"graph\": {}, \"nodes\": [{\"has_standard_radio\": false, \"has_cellular_radio\": false, \"has_satellite_link\": false, \"coord\": [50.0, 95.0], \"id\": \"unit_1\"}], \"links\": []}",
    "{\"directed\": false, \"multigraph\": false, \"graph\": {}, \"nodes\": [{\"has_standard_radio\": false, \"has_cellular_radio\": false, \"has_satellite_link\": false, \"coord\": [50.0, 95.0], \"id\": \"unit_1\"}], \"links\": []}",
    "{\"directed\": false, \"multigraph\": false, \"graph\": {}, \"nodes\": [{\"has_standard_radio\": false, \"has_cellular_radio\": false, \"has_satellite_link\": false, \"coord\": [50.0, 95.0], \"id\": \"unit_1\"}], \"links\": []}",
    "{\"directed\": false, \"multigraph\": false, \"graph\": {}, \"nodes\": [{\"has_standard_radio\": false, \"has_cellular_radio\": false, \"has_satellite_link\": false, \"coord\": [50.0, 95.0], \"id\": \"unit_1\"}], \"links\": []}",
    "{\"directed\": false, \"multigraph\": false, \"graph\": {}, \"nodes\": [{\"has_standard_radio\": false, \"has_cellular_radio\": false, \"has_satellite_link\": false, \"coord\": [50.0, 95.0], \"id\": \"unit_1\"}], \"links\": []}",
    "{\"directed\": false, \"multigraph\": false, \"graph\": {}, \"nodes\": [{\"has_standard_radio\": false, \"has_cellular_radio\": false, \"has_satellite_link\": false, \"coord\": [50.0, 95.0], \"id\": \"unit_1\"}], \"links\": []}",
    "{\"directed\": false, \"multigraph\": false, \"graph\": {}, \"nodes\": [{\"has_standard_radio\": false, \"has_cellular_radio\": false, \"has_satellite_link\": false, \"coord\": [50.0, 95.0], \"id\": \"unit_1\"}], \"links\": []}",
    "{\"directed\": false, \"multigraph\": false, \"graph\": {}, \"nodes\": [{\"has_standard_radio\": false, \"has_cellular_radio\": false, \"has_satellite_link\": false, \"coord\": [50.0, 95.0], \"id\": \"unit_1\"}], \"links\": []}",
    "{\"directed\": false, \"multigraph\": false, \"graph\": {}, \"nodes\": [{\"has_standard_radio\": false, \"has_cellular_radio\": false, \"has_satellite_link\": false, \"coord\": [50.0, 95.0], \"id\": \"unit_1\"}], \"links\": []}",
    "{\"directed\": false, \"multigraph\": false, \"graph\": {}, \"nodes\": [{\"has_standard_radio\": false, \"has_cellular_radio\": false, \"has_satellite_link\": false, \"coord\": [50.0, 95.0], \"id\": \"unit_1\"}], \"links\": []}",
    "{\"directed\": false, \"multigraph\": false, \"graph\": {}, \"nodes\": [{\"has_standard_radio\": false, \"has_cellular_radio\": false, \"has_satellite_link\": false, \"coord\": [50.0, 95.0], \"id\": \"unit_1\"}], \"links\": []}",
    "{\"directed\": false, \"multigraph\": false, \"graph\": {}, \"nodes\": [{\"has_standard_radio\": false, \"has_cellular_radio\": false, \"has_satellite_link\": false, \"coord\": [50.0, 95.0], \"id\": \"unit_1\"}], \"links\": []}",
    "{\"directed\": false, \"multigraph\": false, \"graph\": {}, \"nodes\": [{\"has_standard_radio\": false, \"has_cellular_radio\": false, \"has_satellite_link\": false, \"coord\": [50.0, 95.0], \"id\": \"unit_1\"}], \"links\": []}",
    "{\"directed\": false, \"multigraph\": false, \"graph\": {}, \"nodes\": [{\"has_standard_radio\": false, \"has_cellular_radio\": false, \"has_satellite_link\": false, \"coord\": [50.0, 95.0], \"id\": \"unit_1\"}], \"links\": []}",
    "{\"directed\": false, \"multigraph\": false, \"graph\": {}, \"nodes\": [{\"has_standard_radio\": false, \"has_cellular_radio\": false, \"has_satellite_link\": false, \"coord\": [50.0, 95.0], \"id\": \"unit_1\"}], \"links\": []}",
    "{\"directed\": false, \"multigraph\": false, \"graph\": {}, \"nodes\": [{\"has_standard_radio\": false, \"has_cellular_radio\": false, \"has_satellite_link\": false, \"coord\": [50.0, 95.0], \"id\": \"unit_1\"}], \"links\": []}",
    "{\"directed\": false, \"multigraph\": false, \"graph\": {}, \"nodes\": [{\"has_standard_radio\": false, \"has_cellular_radio\": false, \"has_satellite_link\": false, \"coord\": [50.0, 95.0], \"id\": \"unit_1\"}], \"links\": []}",
    "{\"directed\": false, \"multigraph\": false, \"graph\": {}, \"nodes\": [{\"has_standard_radio\": false, \"has_cellular_radio\": false, \"has_satellite_link\": false, \"coord\": [50.0, 95.0], \"id\": \"unit_1\"}], \"links\": []}",
    "{\"directed\": false, \"multigraph\": false, \"graph\": {}, \"nodes\": [{\"has_standard_radio\": false, \"has_cellular_radio\": false, \"has_satellite_link\": false, \"coord\": [50.0, 95.0], \"id\": \"unit_1\"}], \"links\": []}",
    "{\"directed\": false, \"multigraph\": false, \"graph\": {}, \"nodes\": [{\"has_standard_radio\": false, \"has_cellular_radio\": false, \"has_satellite_link\": false, \"coord\": [50.0, 95.0], \"id\": \"unit_1\"}], \"links\": []}",
    "{\"directed\": false, \"multigraph\": false, \"graph\": {}, \"nodes\": [{\"has_standard_radio\": false, \"has_cellular_radio\": false, \"has_satellite_link\": false, \"coord\": [50.0, 95.0], \"id\": \"unit_1\"}], \"links\": []}",
    "{\"directed\": false, \"multigraph\": false, \"graph\": {}, \"nodes\": [{\"has_standard_radio\": false, \"has_cellular_radio\": false, \"has_satellite_link\": false, \"coord\": [50.0, 95.0], \"id\": \"unit_1\"}], \"links\": []}",
    "{\"directed\": false, \"multigraph\": false, \"graph\": {}, \"nodes\": [{\"has_standard_radio\": false, \"has_cellular_radio\": false, \"has_satellite_link\": false, \"coord\": [50.0, 95.0], \"id\": \"unit_1\"}], \"links\": []}",
    "{\"directed\": false, \"multigraph\": false, \"graph\": {}, \"nodes\": [{\"has_standard_radio\": false, \"has_cellular_radio\": false, \"has_satellite_link\": false, \"coord\": [50.0, 95.0], \"id\": \"unit_1\"}], \"links\": []}",
    "{\"directed\": false, \"multigraph\": false, \"graph\": {}, \"nodes\": [{\"has_standard_radio\": false, \"has_cellular_radio\": false, \"has_satellite_link\": false, \"coord\": [50.0, 95.0], \"id\": \"unit_1\"}], \"links\": []}",
    "{\"directed\": false, \"multigraph\": false, \"graph\": {}, \"nodes\": [{\"has_standard_radio\": false, \"has_cellular_radio\": false, \"has_satellite_link\": false, \"coord\": [50.0, 95.0], \"id\": \"unit_1\"}], \"links\": []}",
    "{\"directed\": false, \"multigraph\": false, \"graph\": {}, \"nodes\": [{\"has_standard_radio\": false, \"has_cellular_radio\": false, \"has_satellite_link\": false, \"coord\": [50.0, 95.0], \"id\": \"unit_1\"}], \"links\": []}",
    "{\"directed\": false, \"multigraph\": false, \"graph\": {}, \"nodes\": [{\"has_standard_radio\": false, \"has_cellular_radio\": false, \"has_satellite_link\": false, \"coord\": [50.0, 95.0], \"id\": \"unit_1\"}], \"links\": []}",
    "{\"directed\": false, \"multigraph\": false, \"graph\": {}, \"nodes\": [{\"has_standard_radio\": false, \"has_cellular_radio\": false, \"has_satellite_link\": false, \"coord\": [50.0, 95.0], \"id\": \"unit_1\"}], \"links\": []}",
    "{\"directed\": false, \"multigraph\": false, \"graph\": {}, \"nodes\": [{\"has_standard_radio\": false, \"has_cellular_radio\": false, \"has_satellite_link\": false, \"coord\": [50.0, 95.0], \"id\": \"unit_1\"}], \"links\": []}",
    "{\"directed\": false, \"multigraph\": false, \"graph\": {}, \"nodes\": [{\"has_standard_radio\": false, \"has_cellular_radio\": false, \"has_satellite_link\": false, \"coord\": [50.0, 95.0], \"id\": \"unit_1\"}], \"links\": []}",
    "{\"directed\": false, \"multigraph\": false, \"graph\": {}, \"nodes\": [{\"has_standard_radio\": false, \"has_cellular_radio\": false, \"has_satellite_link\": false, \"coord\": [50.0, 95.0], \"id\": \"unit_1\"}], \"links\": []}",
    "{\"directed\": false, \"multigraph\": false, \"graph\": {}, \"nodes\": [{\"has_standard_radio\": false, \"has_cellular_radio\": false, \"has_satellite_link\": false, \"coord\": [50.0, 95.0], \"id\": \"unit_1\"}], \"links\": []}",
    "{\"directed\": false, \"multigraph\": false, \"graph\": {}, \"nodes\": [{\"has_standard_radio\": false, \"has_cellular_radio\": false, \"has_satellite_link\": false, \"coord\": [50.0, 95.0], \"id\": \"unit_1\"}], \"links\": []}",
    "{\"directed\": false, \"multigraph\": false, \"graph\": {}, \"nodes\": [{\"has_standard_radio\": false, \"has_cellular_radio\": false, \"has_satellite_link\": false, \"coord\": [50.0, 95.0], \"id\": \"unit_1\"}], \"links\": []}",
    "{\"directed\": false, \"multigraph\": false, \"graph\": {}, \"nodes\": [{\"has_standard_radio\": false, \"has_cellular_radio\": false, \"has_satellite_link\": false, \"coord\": [50.0, 95.0], \"id\": \"unit_1\"}], \"links\": []}",
    "{\"directed\": false, \"multigraph\": false, \"graph\": {}, \"nodes\": [{\"has_standard_radio\": false, \"has_cellular_radio\": false, \"has_satellite_link\": false, \"coord\": [50.0, 95.0], \"id\": \"unit_1\"}], \"links\": []}",
    "{\"directed\": false, \"multigraph\": false, \"graph\": {}, \"nodes\": [{\"has_standard_radio\": false, \"has_cellular_radio\": false, \"has_satellite_link\": false, \"coord\": [50.0, 95.0], \"id\": \"unit_1\"}], \"links\": []}",
    "{\"directed\": false, \"multigraph\": false, \"graph\": {}, \"nodes\": [{\"has_standard_radio\": false, \"has_cellular_radio\": false, \"has_satellite_link\": false, \"coord\": [50.0, 95.0], \"id\": \"unit_1\"}], \"links\": []}",
    "{\"directed\": false, \"multigraph\": false, \"graph\": {}, \"nodes\": [{\"has_standard_radio\": false, \"has_cellular_radio\": false, \"has_satellite_link\": false, \"coord\": [50.0, 95.0], \"id\": \"unit_1\"}], \"links\": []}",
    "{\"directed\": false, \"multigraph\": false, \"graph\": {}, \"nodes\": [{\"has_standard_radio\": false, \"has_cellular_radio\": false, \"has_satellite_link\": false, \"coord\": [50.0, 95.0], \"id\": \"unit_1\"}], \"links\": []}",
    "{\"directed\": false, \"multigraph\": false, \"graph\": {}, \"nodes\": [{\"has_standard_radio\": false, \"has_cellular_radio\": false, \"has_satellite_link\": false, \"coord\": [50.0, 95.0], \"id\": \"unit_1\"}], \"links\": []}",
    "{\"directed\": false, \"multigraph\": false, \"graph\": {}, \"nodes\": [{\"has_standard_radio\": false, \"has_cellular_radio\": false, \"has_satellite_link\": false, \"coord\": [50.0, 95.0], \"id\": \"unit_1\"}], \"links\": []}",
    "{\"directed\": false, \"multigraph\": false, \"graph\": {}, \"nodes\": [{\"has_standard_radio\": false, \"has_cellular_radio\": false, \"has_satellite_link\": false, \"coord\": [50.0, 95.0], \"id\": \"unit_1\"}], \"links\": []}",
    "{\"directed\": false, \"multigraph\": false, \"graph\": {}, \"nodes\": [{\"has_standard_radio\": false, \"has_cellular_radio\": false, \"has_satellite_link\": false, \"coord\": [50.0, 95.0], \"id\": \"unit_1\"}], \"links\": []}",
    "{\"directed\": false, \"multigraph\": false, \"graph\": {}, \"nodes\": [{\"has_standard_radio\": false, \"has_cellular_radio\": false, \"has_satellite_link\": false, \"coord\": [50.0, 95.0], \"id\": \"unit_1\"}], \"links\": []}",
    "{\"directed\": false, \"multigraph\": false, \"graph\": {}, \"nodes\": [{\"has_standard_radio\": false, \"has_cellular_radio\": false, \"has_satellite_link\": false, \"coord\": [50.0, 95.0], \"id\": \"unit_1\"}], \"links\": []}",
    "{\"directed\": false, \"multigraph\": false, \"graph\": {}, \"nodes\": [{\"has_standard_radio\": false, \"has_cellular_radio\": false, \"has_satellite_link\": false, \"coord\": [50.0, 95.0], \"id\": \"unit_1\"}], \"links\": []}",
    "{\"directed\": false, \"multigraph\": false, \"graph\": {}, \"nodes\": [{\"has_standard_radio\": false, \"has_cellular_radio\": false, \"has_satellite_link\": false, \"coord\": [50.0, 95.0], \"id\": \"unit_1\"}], \"links\": []}",
    "{\"directed\": false, \"multigraph\": false, \"graph\": {}, \"nodes\": [{\"has_standard_radio\": false, \"has_cellular_radio\": false, \"has_satellite_link\": false, \"coord\": [50.0, 95.0], \"id\": \"unit_1\"}], \"links\": []}",
    "{\"directed\": false, \"multigraph\": false, \"graph\": {}, \"nodes\": [{\"has_standard_radio\": false, \"has_cellular_radio\": false, \"has_satellite_link\": false, \"coord\": [50.0, 95.0], \"id\": \"unit_1\"}], \"links\": []}",
    "{\"directed\": false, \"multigraph\": false, \"graph\": {}, \"nodes\": [{\"has_standard_radio\": false, \"has_cellular_radio\": false, \"has_satellite_link\": false, \"coord\": [50.0, 95.0], \"id\": \"unit_1\"}], \"links\": []}",
    "{\"directed\": false, \"multigraph\": false, \"graph\": {}, \"nodes\": [{\"has_standard_radio\": false, \"has_cellular_radio\": false, \"has_satellite_link\": false, \"coord\": [50.0, 95.0], \"id\": \"unit_1\"}], \"links\": []}",
    "{\"directed\": false, \"multigraph\": false, \"graph\": {}, \"nodes\": [{\"has_standard_radio\": false, \"has_cellular_radio\": false, \"has_satellite_link\": false, \"coord\": [50.0, 95.0], \"id\": \"unit_1\"}], \"links\": []}",
    "{\"directed\": false, \"multigraph\": false, \"graph\": {}, \"nodes\": [{\"has_standard_radio\": false, \"has_cellular_radio\": false, \"has_satellite_link\": false, \"coord\": [50.0, 95.0], \"id\": \"unit_1\"}], \"links\": []}",
    "{\"directed\": false, \"multigraph\": false, \"graph\": {}, \"nodes\": [{\"has_standard_radio\": false, \"has_cellular_radio\": false, \"has_satellite_link\": false, \"coord\": [50.0, 95.0], \"id\": \"unit_1\"}], \"links\": []}",
    "{\"directed\": false, \"multigraph\": false, \"graph\": {}, \"nodes\": [{\"has_standard_radio\": false, \"has_cellular_radio\": false, \"has_satellite_link\": false, \"coord\": [50.0, 95.0], \"id\": \"unit_1\"}], \"links\": []}",
    "{\"directed\": false, \"multigraph\": false, \"graph\": {}, \"nodes\": [{\"has_standard_radio\": false, \"has_cellular_radio\": false, \"has_satellite_link\": false, \"coord\": [50.0, 95.0], \"id\": \"unit_1\"}], \"links\": []}",
    "{\"directed\": false, \"multigraph\": false, \"graph\": {}, \"nodes\": [{\"has_standard_radio\": false, \"has_cellular_radio\": false, \"has_satellite_link\": false, \"coord\": [50.0, 95.0], \"id\": \"unit_1\"}], \"links\": []}",
    "{\"directed\": false, \"multigraph\": false, \"graph\": {}, \"nodes\": [{\"has_standard_radio\": false, \"has_cellular_radio\": false, \"has_satellite_link\": false, \"coord\": [50.0, 95.0], \"id\": \"unit_1\"}], \"links\": []}",
    "{\"directed\": false, \"multigraph\": false, \"graph\": {}, \"nodes\": [{\"has_standard_radio\": false, \"has_cellular_radio\": false, \"has_satellite_link\": false, \"coord\": [50.0, 95.0], \"id\": \"unit_1\"}], \"links\": []}",
    "{\"directed\": false, \"multigraph\": false, \"graph\": {}, \"nodes\": [{\"has_standard_radio\": false, \"has_cellular_radio\": false, \"has_satellite_link\": false, \"coord\": [50.0, 95.0], \"id\": \"unit_1\"}], \"links\": []}",
    "{\"directed\": false, \"multigraph\": false, \"graph\": {}, \"nodes\": [{\"has_standard_radio\": false, \"has_cellular_radio\": false, \"has_satellite_link\": false, \"coord\": [50.0, 95.0], \"id\": \"unit_1\"}], \"links\": []}",
    "{\"directed\": false, \"multigraph\": false, \"graph\": {}, \"nodes\": [{\"has_standard_radio\": false, \"has_cellular_radio\": false, \"has_satellite_link\": false, \"coord\": [50.0, 95.0], \"id\": \"unit_1\"}], \"links\": []}",
    "{\"directed\": false, \"multigraph\": false, \"graph\": {}, \"nodes\": [{\"has_standard_radio\": false, \"has_cellular_radio\": false, \"has_satellite_link\": false, \"coord\": [50.0, 95.0], \"id\": \"unit_1\"}], \"links\": []}",
    "{\"directed\": false, \"multigraph\": false, \"graph\": {}, \"nodes\": [{\"has_standard_radio\": false, \"has_cellular_radio\": false, \"has_satellite_link\": false, \"coord\": [50.0, 95.0], \"id\": \"unit_1\"}], \"links\": []}",
    "{\"directed\": false, \"multigraph\": false, \"graph\": {}, \"nodes\": [{\"has_standard_radio\": false, \"has_cellular_radio\": false, \"has_satellite_link\": false, \"coord\": [50.0, 95.0], \"id\": \"unit_1\"}], \"links\": []}",
    "{\"directed\": false, \"multigraph\": false, \"graph\": {}, \"nodes\": [{\"has_standard_radio\": false, \"has_cellular_radio\": false, \"has_satellite_link\": false, \"coord\": [50.0, 95.0], \"id\": \"unit_1\"}], \"links\": []}",
    "{\"directed\": false, \"multigraph\": false, \"graph\": {}, \"nodes\": [{\"has_standard_radio\": false, \"has_cellular_radio\": false, \"has_satellite_link\": false, \"coord\": [50.0, 95.0], \"id\": \"unit_1\"}], \"links\": []}",
    "{\"directed\": false, \"multigraph\": false, \"graph\": {}, \"nodes\": [{\"has_standard_radio\": false, \"has_cellular_radio\": false, \"has_satellite_link\": false, \"coord\": [50.0, 95.0], \"id\": \"unit_1\"}], \"links\": []}",
    "{\"directed\": false, \"multigraph\": false, \"graph\": {}, \"nodes\": [{\"has_standard_radio\": false, \"has_cellular_radio\": false, \"has_satellite_link\": false, \"coord\": [50.0, 95.0], \"id\": \"unit_1\"}], \"links\": []}",
    "{\"directed\": false, \"multigraph\": false, \"graph\": {}, \"nodes\": [{\"has_standard_radio\": false, \"has_cellular_radio\": false, \"has_satellite_link\": false, \"coord\": [50.0, 95.0], \"id\": \"unit_1\"}], \"links\": []}",
    "{\"directed\": false, \"multigraph\": false, \"graph\": {}, \"nodes\": [{\"has_standard_radio\": false, \"has_cellular_radio\": false, \"has_satellite_link\": false, \"coord\": [50.0, 95.0], \"id\": \"unit_1\"}], \"links\": []}",
    "{\"directed\": false, \"multigraph\": false, \"graph\": {}, \"nodes\": [{\"has_standard_radio\": false, \"has_cellular_radio\": false, \"has_satellite_link\": false, \"coord\": [50.0, 95.0], \"id\": \"unit_1\"}], \"links\": []}",
    "{\"directed\": false, \"multigraph\": false, \"graph\": {}, \"nodes\": [{\"has_standard_radio\": false, \"has_cellular_radio\": false, \"has_satellite_link\": false, \"coord\": [50.0, 95.0], \"id\": \"unit_1\"}], \"links\": []}",
    "{\"directed\": false, \"multigraph\": false, \"graph\": {}, \"nodes\": [{\"has_standard_radio\": false, \"has_cellular_radio\": false, \"has_satellite_link\": false, \"coord\": [50.0, 95.0], \"id\": \"unit_1\"}], \"links\": []}",
    "{\"directed\": false, \"multigraph\": false, \"graph\": {}, \"nodes\": [{\"has_standard_radio\": false, \"has_cellular_radio\": false, \"has_satellite_link\": false, \"coord\": [50.0, 95.0], \"id\": \"unit_1\"}], \"links\": []}",
    "{\"directed\": false, \"multigraph\": false, \"graph\": {}, \"nodes\": [{\"has_standard_radio\": false, \"has_cellular_radio\": false, \"has_satellite_link\": false, \"coord\": [50.0, 95.0], \"id\": \"unit_1\"}], \"links\": []}",
    "{\"directed\": false, \"multigraph\": false, \"graph\": {}, \"nodes\": [{\"has_standard_radio\": false, \"has_cellular_radio\": false, \"has_satellite_link\": false, \"coord\": [50.0, 95.0], \"id\": \"unit_1\"}], \"links\": []}",
    "{\"directed\": false, \"multigraph\": false, \"graph\": {}, \"nodes\": [{\"has_standard_radio\": false, \"has_cellular_radio\": false, \"has_satellite_link\": false, \"coord\": [50.0, 95.0], \"id\": \"unit_1\"}], \"links\": []}",
    "{\"directed\": false, \"multigraph\": false, \"graph\": {}, \"nodes\": [{\"has_standard_radio\": false, \"has_cellular_radio\": false, \"has_satellite_link\": false, \"coord\": [50.0, 95.0], \"id\": \"unit_1\"}], \"links\": []}"
]